Workbook
Name Bin_Card_Bal.: 'STOCK CONTROL SHEET'!$F$3:$F$172
Name COMP.STOREPhysicalBal.: 'STOCK CONTROL SHEET'!$I$39:$I$124
Name COMP.STOREPRIMARY: 'STOCK CONTROL SHEET'!$B$39:$N$124
Name COMP.STOREReorderLevels: 'STOCK CONTROL SHEET'!$M$39:$M$124
Name COMPMaterialNo: 'STOCK CONTROL SHEET'!$B$39:$B$124
Name Details: 'STOCK CONTROL SHEET'!$B$4:$D$172
Name Details: 'STOCK CONTROL SHEET'!$B$4:$D$172,'STOCK CONTROL SHEET'!$I$4:$I$172
Name INOUTCODE: 'COMPUTER STORE'!$D$3:$D$11
Name INOUTCODE: MAINTENANCE!$D$3:$D$11
Name INOUTCODE: 'SF STORE'!$D$3:$D$123
Name INOUTQTY: 'COMPUTER STORE'!$G$3:$G$11
Name INOUTQTY: MAINTENANCE!$G$3:$G$11
Name INOUTQTY: 'SF STORE'!$G$3:$G$123
Name ItemDescription: 'STOCK CONTROL SHEET'!$C$4:$C$172
Name MAINT.STOREPhysicalStockBal.: 'STOCK CONTROL SHEET'!$I$125:$I$172
Name MAINT.STOREPRIMARY: 'STOCK CONTROL SHEET'!$B$125:$N$172
Name MAINT.STOREReorderLevels: 'STOCK CONTROL SHEET'!$M$125:$M$172
Name MAINTMaterialNo: 'STOCK CONTROL SHEET'!$B$125:$B$172
Name NativeTimeline_Date: #N/A
Name NativeTimeline_Date1: #N/A
Name NativeTimeline_Date2: #N/A
Name NativeTimeline_Date3: #N/A
Name Opening_S5_Bin_Card_Bal.: 'STOCK CONTROL SHEET'!$E$4:$E$172
Name Physical_Stock_Bal.: SF.STOREPRIMARY[Physical Stock Bal.]
Name Qty._Deficit: SF.STOREPRIMARY[Qty. Deficit]
Name Qty._Surplus: 'STOCK CONTROL SHEET'!$K:$K
Name Reorder_Levels: 'STOCK CONTROL SHEET'!$M:$M
Name ROLL: SF.STOREPRIMARY[Unit of Issue]
Name Running_Balance: 'COMPUTER STORE'!$J:$J
Name Running_Balance: MAINTENANCE!$J:$J
Name Running_Balance: 'SF STORE'!$J:$J
Name SF.STORE.TABLE: SF.STOREPRIMARY[]
Name SFMaterialNo: SF.STOREPRIMARY[Material No]
Name Slicer_Department: #N/A
Name Slicer_Department1: #N/A
Name Slicer_Department2: #N/A
Name Slicer_Department3: #N/A
Name Slicer_In_Out_Qty: #N/A
Name Slicer_In_Out_Qty1: #N/A
Name Slicer_In_Out_Qty2: #N/A
Name Slicer_In_Out_Qty3: #N/A
Name Slicer_Item_Description: #N/A
Name Slicer_Item_Description1: #N/A
Name Slicer_Item_Description2: #N/A
Name Slicer_Item_Description3: #N/A
Name Slicer_Store: #N/A
Name Slicer_Type: #N/A
Name Slicer_Type1: #N/A
Name Slicer_Type2: #N/A
Name Slicer_Type3: #N/A
Name Slicer_Value_of_Deficiency: #N/A
Name Slicer_Value_of_Surplus: #N/A
Name TransactionType: 'COMPUTER STORE'!$M$4:$M$6
Name TransactionType: MAINTENANCE!$M$4:$M$6
Name TransactionType: 'SF STORE'!$M$4:$M$6
Name Type: UnitsTable[Type]
Name Type: ComputerStoreUnitsTable[Type]
Name Type: MAINTENANCEUnitsTable[Type]
Name Type: UnitsTable[Type]
Name Type: UnitsTable[Type]

Sheet STOCK CONTROL SHEET
A1: STORE | B1: STOCK CONTROL SHEET FOR STATIONERY|SF|COMPUTER & MAINTENANCE STORE
B2: PRIMARY STOCK CONTROL DATA FOR THREE STORES
A3: SF STORE | B3: Material No | C3: Item Description | D3: Unit of Issue | E3: Opening S5 Bin Card Bal. | F3: In&Out Qty | G3: Bin Card Balance | H3: Opening Physical Stock Count. | I3: Physical Stock Bal. | J3: Qty. Deficit | K3: Qty. Surplus | L3: Reorder Quantity | M3: Reorder Levels | N3: Remarks
B4: 282014 | C4: Tissue Papers | D4: ROLL | F4: =SUMIF(UnitsTable[Item Description],'STOCK CONTROL SHEET'!C4,UnitsTable[Running Balance]) -> 0 | G4: =IF(SUM(E4,F4)<0,"",SUM(E4,F4)) -> 0 | I4: =IF(SUM(H4,F4)<0,"",SUM(H4,F4)) -> 0 | J4: =IF(G4-I4<=0,"",G4-I4) | K4: =IF(I4-G4<=0,"",I4-G4) | L4: 12720 | M4: 500 | N4: =IF(I4<=M4,"Reorder","Available") -> Reorder
B5: 100126 | C5: Administration Folders | D5: PCS | E5: 375 | F5: =SUMIF(UnitsTable[Item Description],'STOCK CONTROL SHEET'!C5,UnitsTable[Running Balance]) -> 0 | G5: =IF(SUM(E5,F5)<0,"",SUM(E5,F5)) -> 375 | H5: 0 | I5: =IF(SUM(H5,F5)<0,"",SUM(H5,F5)) -> 0 | J5: =IF(G5-I5<=0,"",G5-I5) -> 375 | K5: =IF(I5-G5<=0,"",I5-G5) | L5: 1800 | M5: 450 | N5: =IF(I5<=M5,"Reorder","Available") -> Reorder
B6: 100128 | C6: Age Benefit Folders | D6: PCS | E6: 100 | F6: =SUMIF(UnitsTable[Item Description],'STOCK CONTROL SHEET'!C6,UnitsTable[Running Balance]) -> 0 | G6: =IF(SUM(E6,F6)<0,"",SUM(E6,F6)) -> 100 | H6: 176 | I6: =IF(SUM(H6,F6)<0,"",SUM(H6,F6)) -> 176 | J6: =IF(G6-I6<=0,"",G6-I6) | K6: =IF(I6-G6<=0,"",I6-G6) -> 76 | L6: 20000 | M6: 4500 | N6: =IF(I6<=M6,"Reorder","Available") -> Reorder
B7: 100216 | C7: App. For Personal Exemption Forms | D7: PCS | F7: =SUMIF(UnitsTable[Item Description],'STOCK CONTROL SHEET'!C7,UnitsTable[Running Balance]) -> 0 | G7: =IF(SUM(E7,F7)<0,"",SUM(E7,F7)) -> 0 | I7: =IF(SUM(H7,F7)<0,"",SUM(H7,F7)) -> 0 | J7: =IF(G7-I7<=0,"",G7-I7) | K7: =IF(I7-G7<=0,"",I7-G7) | M7: 3000 | N7: =IF(I7<=M7,"Reorder","Available") -> Reorder
B8: 100139 | C8: App. For Employer SF/001 | D8: PCS | E8: 12750 | F8: =SUMIF(UnitsTable[Item Description],'STOCK CONTROL SHEET'!C8,UnitsTable[Running Balance]) -> -4000 | G8: =IF(SUM(E8,F8)<0,"",SUM(E8,F8)) -> 8750 | H8: 10000 | I8: =IF(SUM(H8,F8)<0,"",SUM(H8,F8)) -> 6000 | J8: =IF(G8-I8<=0,"",G8-I8) -> 2750 | K8: =IF(I8-G8<=0,"",I8-G8) | L8: 60000 | M8: 15000 | N8: =IF(I8<=M8,"Reorder","Available") -> Reorder
B9: 100218 | C9: Ben. App. Forms SF/001 | D9: PCS | E9: 14800 | F9: =SUMIF(UnitsTable[Item Description],'STOCK CONTROL SHEET'!C9,UnitsTable[Running Balance]) -> -5850 | G9: =IF(SUM(E9,F9)<0,"",SUM(E9,F9)) -> 8950 | H9: 11000 | I9: =IF(SUM(H9,F9)<0,"",SUM(H9,F9)) -> 5150 | J9: =IF(G9-I9<=0,"",G9-I9) -> 3800 | K9: =IF(I9-G9<=0,"",I9-G9) | L9: 30000 | M9: 7500 | N9: =IF(I9<=M9,"Reorder","Available") -> Reorder
B10: 100220 | C10: Payment of Benefit Forms/004 | D10: PCS | E10: 35 | F10: =SUMIF(UnitsTable[Item Description],'STOCK CONTROL SHEET'!C10,UnitsTable[Running Balance]) -> -5300 | G10: =IF(SUM(E10,F10)<0,"",SUM(E10,F10)) | H10: 29 | I10: =IF(SUM(H10,F10)<0,"",SUM(H10,F10)) | J10: =IF(G10-I10<=0,"",G10-I10) -> #VALUE! | K10: =IF(I10-G10<=0,"",I10-G10) -> #VALUE! | L10: 30000 | M10: 7500 | N10: =IF(I10<=M10,"Reorder","Available") -> Available
B11: 100210 | C11: Claim Confirmation SF/D/005 | D11: PCS | F11: =SUMIF(UnitsTable[Item Description],'STOCK CONTROL SHEET'!C11,UnitsTable[Running Balance]) -> 0 | G11: =IF(SUM(E11,F11)<0,"",SUM(E11,F11)) -> 0 | I11: =IF(SUM(H11,F11)<0,"",SUM(H11,F11)) -> 0 | J11: =IF(G11-I11<=0,"",G11-I11) | K11: =IF(I11-G11<=0,"",I11-G11) | L11: 30000 | M11: 7500 | N11: =IF(I11<=M11,"Reorder","Available") -> Reorder
B12: 100162 | C12: Confidential Folders Pink | D12: PCS | E12: 170 | F12: =SUMIF(UnitsTable[Item Description],'STOCK CONTROL SHEET'!C12,UnitsTable[Running Balance]) -> 0 | G12: =IF(SUM(E12,F12)<0,"",SUM(E12,F12)) -> 170 | H12: 5 | I12: =IF(SUM(H12,F12)<0,"",SUM(H12,F12)) -> 5 | J12: =IF(G12-I12<=0,"",G12-I12) -> 165 | K12: =IF(I12-G12<=0,"",I12-G12) | L12: 1000 | M12: 250 | N12: =IF(I12<=M12,"Reorder","Available") -> Reorder
B13: 100144 | C13: Dummy B Certificate | D13: PCS | E13: 201 | F13: =SUMIF(UnitsTable[Item Description],'STOCK CONTROL SHEET'!C13,UnitsTable[Running Balance]) -> 0 | G13: =IF(SUM(E13,F13)<0,"",SUM(E13,F13)) -> 201 | H13: 201 | I13: =IF(SUM(H13,F13)<0,"",SUM(H13,F13)) -> 201 | J13: =IF(G13-I13<=0,"",G13-I13) | K13: =IF(I13-G13<=0,"",I13-G13) | L13: 300 | M13: 100 | N13: =IF(I13<=M13,"Reorder","Available") -> Available
B14: 100125 | C14: Empty Cartons | D14: NO | E14: 497 | F14: =SUMIF(UnitsTable[Item Description],'STOCK CONTROL SHEET'!C14,UnitsTable[Running Balance]) -> 0 | G14: =IF(SUM(E14,F14)<0,"",SUM(E14,F14)) -> 497 | H14: 367 | I14: =IF(SUM(H14,F14)<0,"",SUM(H14,F14)) -> 367 | J14: =IF(G14-I14<=0,"",G14-I14) -> 130 | K14: =IF(I14-G14<=0,"",I14-G14) | L14: 200 | M14: 100 | N14: =IF(I14<=M14,"Reorder","Available") -> Available
B15: 100123 | C15: Envelopes A4 | D15: PCS | E15: 12045 | F15: =SUMIF(UnitsTable[Item Description],'STOCK CONTROL SHEET'!C15,UnitsTable[Running Balance]) -> -2400 | G15: =IF(SUM(E15,F15)<0,"",SUM(E15,F15)) -> 9645 | H15: 15251 | I15: =IF(SUM(H15,F15)<0,"",SUM(H15,F15)) -> 12851 | J15: =IF(G15-I15<=0,"",G15-I15) | K15: =IF(I15-G15<=0,"",I15-G15) -> 3206 | L15: 40000 | M15: 9000 | N15: =IF(I15<=M15,"Reorder","Available") -> Available
B16: 100228 | C16: A3 Security Envelopes | D16: PCS | E16: 10 | F16: =SUMIF(UnitsTable[Item Description],'STOCK CONTROL SHEET'!C16,UnitsTable[Running Balance]) -> 0 | G16: =IF(SUM(E16,F16)<0,"",SUM(E16,F16)) -> 10 | H16: 0 | I16: =IF(SUM(H16,F16)<0,"",SUM(H16,F16)) -> 0 | J16: =IF(G16-I16<=0,"",G16-I16) -> 10 | K16: =IF(I16-G16<=0,"",I16-G16) | L16: 1600 | M16: 600 | N16: =IF(I16<=M16,"Reorder","Available") -> Reorder
B17: 100124 | C17: Envelopes A3 (16*12) White | D17: PCS | E17: 1336 | F17: =SUMIF(UnitsTable[Item Description],'STOCK CONTROL SHEET'!C17,UnitsTable[Running Balance]) -> -250 | G17: =IF(SUM(E17,F17)<0,"",SUM(E17,F17)) -> 1086 | H17: 1361 | I17: =IF(SUM(H17,F17)<0,"",SUM(H17,F17)) -> 1111 | J17: =IF(G17-I17<=0,"",G17-I17) | K17: =IF(I17-G17<=0,"",I17-G17) -> 25 | L17: 2000 | M17: 450 | N17: =IF(I17<=M17,"Reorder","Available") -> Available
B18: 100122 | C18: Envelopes A5 | D18: PCS | E18: 14646 | F18: =SUMIF(UnitsTable[Item Description],'STOCK CONTROL SHEET'!C18,UnitsTable[Running Balance]) -> -1910 | G18: =IF(SUM(E18,F18)<0,"",SUM(E18,F18)) -> 12736 | H18: 11067 | I18: =IF(SUM(H18,F18)<0,"",SUM(H18,F18)) -> 9157 | J18: =IF(G18-I18<=0,"",G18-I18) -> 3579 | K18: =IF(I18-G18<=0,"",I18-G18) | L18: 15000 | M18: 3750 | N18: =IF(I18<=M18,"Reorder","Available") -> Available
B19: 100130 | C19: Emigration Benefit Folders | D19: PCS | E19: 2210 | F19: =SUMIF(UnitsTable[Item Description],'STOCK CONTROL SHEET'!C19,UnitsTable[Running Balance]) -> -120 | G19: =IF(SUM(E19,F19)<0,"",SUM(E19,F19)) -> 2090 | H19: 2498 | I19: =IF(SUM(H19,F19)<0,"",SUM(H19,F19)) -> 2378 | J19: =IF(G19-I19<=0,"",G19-I19) | K19: =IF(I19-G19<=0,"",I19-G19) -> 288 | L19: 270 | M19: 68 | N19: =IF(I19<=M19,"Reorder","Available") -> Available
B20: 100138 | C20: Fingerprint Forms SF/003 | D20: PCS | E20: 31 | F20: =SUMIF(UnitsTable[Item Description],'STOCK CONTROL SHEET'!C20,UnitsTable[Running Balance]) -> -4000 | G20: =IF(SUM(E20,F20)<0,"",SUM(E20,F20)) | H20: 9 | I20: =IF(SUM(H20,F20)<0,"",SUM(H20,F20)) | J20: =IF(G20-I20<=0,"",G20-I20) -> #VALUE! | K20: =IF(I20-G20<=0,"",I20-G20) -> #VALUE! | L20: 90000 | M20: 22500 | N20: =IF(I20<=M20,"Reorder","Available") -> Available
B21: 100221 | C21: Funeral Grant Forms 006 | D21: PCS | E21: 445 | F21: =SUMIF(UnitsTable[Item Description],'STOCK CONTROL SHEET'!C21,UnitsTable[Running Balance]) -> -180 | G21: =IF(SUM(E21,F21)<0,"",SUM(E21,F21)) -> 265 | H21: 222 | I21: =IF(SUM(H21,F21)<0,"",SUM(H21,F21)) -> 42 | J21: =IF(G21-I21<=0,"",G21-I21) -> 223 | K21: =IF(I21-G21<=0,"",I21-G21) | L21: 5000 | M21: 1250 | N21: =IF(I21<=M21,"Reorder","Available") -> Reorder
B22: 100155 | C22: Finance Account Folders | D22: PCS | E22: 104 | F22: =SUMIF(UnitsTable[Item Description],'STOCK CONTROL SHEET'!C22,UnitsTable[Running Balance]) -> -60 | G22: =IF(SUM(E22,F22)<0,"",SUM(E22,F22)) -> 44 | H22: 62 | I22: =IF(SUM(H22,F22)<0,"",SUM(H22,F22)) -> 2 | J22: =IF(G22-I22<=0,"",G22-I22) -> 42 | K22: =IF(I22-G22<=0,"",I22-G22) | L22: 500 | M22: 125 | N22: =IF(I22<=M22,"Reorder","Available") -> Reorder
B23: 100219 | C23: Invalidity Ben. Forms/002 | D23: PCS | E23: 33218 | F23: =SUMIF(UnitsTable[Item Description],'STOCK CONTROL SHEET'!C23,UnitsTable[Running Balance]) -> 0 | G23: =IF(SUM(E23,F23)<0,"",SUM(E23,F23)) -> 33218 | H23: 9100 | I23: =IF(SUM(H23,F23)<0,"",SUM(H23,F23)) -> 9100 | J23: =IF(G23-I23<=0,"",G23-I23) -> 24118 | K23: =IF(I23-G23<=0,"",I23-G23) | L23: 3000 | M23: 1500 | N23: =IF(I23<=M23,"Reorder","Available") -> Available
... B26: 100145 | C26: Membership Cards (Blank) | D26: PCS | E26: 473900 | F26: =SUMIF(UnitsTable[Item Description],'STOCK CONTROL SHEET'!C26,UnitsTable[Running Balance]) -> -43000 | G26: =IF(SUM(E26,F26)<0,"",SUM(E26,F26)) -> 430900 | H26: 512500 | I26: =IF(SUM(H26,F26)<0,"",SUM(H26,F26)) -> 469500 | J26: =IF(G26-I26<=0,"",G26-I26) | K26: =IF(I26-G26<=0,"",I26-G26) -> 38600 | L26: 600000 | M26: 154000 | N26: =IF(I26<=M26,"Reorder","Available") -> Available
B27: 100205 | C27: Employee Registration 003 | D27: PCS | E27: 5 | F27: =SUMIF(UnitsTable[Item Description],'STOCK CONTROL SHEET'!C27,UnitsTable[Running Balance]) -> 0 | G27: =IF(SUM(E27,F27)<0,"",SUM(E27,F27)) -> 5 | H27: 5 | I27: =IF(SUM(H27,F27)<0,"",SUM(H27,F27)) -> 5 | J27: =IF(G27-I27<=0,"",G27-I27) | K27: =IF(I27-G27<=0,"",I27-G27) | N27: =IF(I27<=M27,"Reorder","Available") -> Available
B28: 100164 | C28: Verification of Claim SF 87 | D28: PCS | E28: 36340 | F28: =SUMIF(UnitsTable[Item Description],'STOCK CONTROL SHEET'!C28,UnitsTable[Running Balance]) -> 0 | G28: =IF(SUM(E28,F28)<0,"",SUM(E28,F28)) -> 36340 | H28: 36340 | I28: =IF(SUM(H28,F28)<0,"",SUM(H28,F28)) -> 36340 | J28: =IF(G28-I28<=0,"",G28-I28) | K28: =IF(I28-G28<=0,"",I28-G28) | L28: 30000 | M28: 3000 | N28: =IF(I28<=M28,"Reorder","Available") -> Available
B29: 100211 | C29: Survivor Ben. Form | D29: PCS | E29: 4910 | F29: =SUMIF(UnitsTable[Item Description],'STOCK CONTROL SHEET'!C29,UnitsTable[Running Balance]) -> -1400 | G29: =IF(SUM(E29,F29)<0,"",SUM(E29,F29)) -> 3510 | H29: 4900 | I29: =IF(SUM(H29,F29)<0,"",SUM(H29,F29)) -> 3500 | J29: =IF(G29-I29<=0,"",G29-I29) -> 10 | K29: =IF(I29-G29<=0,"",I29-G29) | M29: 1500 | N29: =IF(I29<=M29,"Reorder","Available") -> Available
B30: 100222 | C30: Unsound Mind DF/007 | D30: PCS | F30: =SUMIF(UnitsTable[Item Description],'STOCK CONTROL SHEET'!C30,UnitsTable[Running Balance]) -> 0 | G30: =IF(SUM(E30,F30)<0,"",SUM(E30,F30)) -> 0 | I30: =IF(SUM(H30,F30)<0,"",SUM(H30,F30)) -> 0 | J30: =IF(G30-I30<=0,"",G30-I30) | K30: =IF(I30-G30<=0,"",I30-G30) | N30: =IF(I30<=M30,"Reorder","Available") -> Reorder
B31: 26 | C31: Plastic Bags A4 | D31: PCS | E31: 20 | F31: =SUMIF(UnitsTable[Item Description],'STOCK CONTROL SHEET'!C31,UnitsTable[Running Balance]) -> 0 | G31: =IF(SUM(E31,F31)<0,"",SUM(E31,F31)) -> 20 | H31: 68 | I31: =IF(SUM(H31,F31)<0,"",SUM(H31,F31)) -> 68 | J31: =IF(G31-I31<=0,"",G31-I31) | K31: =IF(I31-G31<=0,"",I31-G31) -> 48 | N31: =IF(I31<=M31,"Reorder","Available") -> Available
B32: 27 | C32: Plastic Bags A3 | D32: PCS | E32: 0 | F32: =SUMIF(UnitsTable[Item Description],'STOCK CONTROL SHEET'!C32,UnitsTable[Running Balance]) -> 0 | G32: =IF(SUM(E32,F32)<0,"",SUM(E32,F32)) -> 0 | H32: 1500 | I32: =IF(SUM(H32,F32)<0,"",SUM(H32,F32)) -> 1500 | J32: =IF(G32-I32<=0,"",G32-I32) | K32: =IF(I32-G32<=0,"",I32-G32) -> 1500 | N32: =IF(I32<=M32,"Reorder","Available") -> Available
B33: 100181 | C33: Registration Gen. Folders | D33: PCS | E33: 26065 | F33: =SUMIF(UnitsTable[Item Description],'STOCK CONTROL SHEET'!C33,UnitsTable[Running Balance]) -> -2700 | G33: =IF(SUM(E33,F33)<0,"",SUM(E33,F33)) -> 23365 | H33: 23400 | I33: =IF(SUM(H33,F33)<0,"",SUM(H33,F33)) -> 20700 | J33: =IF(G33-I33<=0,"",G33-I33) -> 2665 | K33: =IF(I33-G33<=0,"",I33-G33) | L33: 400000 | M33: 9000 | N33: =IF(I33<=M33,"Reorder","Available") -> Available
B34: 100213 | C34: Schedule of Contribution | D34: PCS | E34: 33298 | F34: =SUMIF(UnitsTable[Item Description],'STOCK CONTROL SHEET'!C34,UnitsTable[Running Balance]) -> -1000 | G34: =IF(SUM(E34,F34)<0,"",SUM(E34,F34)) -> 32298 | H34: 33298 | I34: =IF(SUM(H34,F34)<0,"",SUM(H34,F34)) -> 32298 | J34: =IF(G34-I34<=0,"",G34-I34) | K34: =IF(I34-G34<=0,"",I34-G34) | L34: 50000 | M34: 12500 | N34: =IF(I34<=M34,"Reorder","Available") -> Available
B35: 100177 | C35: Survivor Benefit Folders | D35: PCS | E35: 425 | F35: =SUMIF(UnitsTable[Item Description],'STOCK CONTROL SHEET'!C35,UnitsTable[Running Balance]) -> 0 | G35: =IF(SUM(E35,F35)<0,"",SUM(E35,F35)) -> 425 | H35: 679 | I35: =IF(SUM(H35,F35)<0,"",SUM(H35,F35)) -> 679 | J35: =IF(G35-I35<=0,"",G35-I35) | K35: =IF(I35-G35<=0,"",I35-G35) -> 254 | M35: 1250 | N35: =IF(I35<=M35,"Reorder","Available") -> Reorder
B36: 100159 | C36: Union Medical Cover Folders | D36: PCS | E36: 0 | F36: =SUMIF(UnitsTable[Item Description],'STOCK CONTROL SHEET'!C36,UnitsTable[Running Balance]) -> 0 | G36: =IF(SUM(E36,F36)<0,"",SUM(E36,F36)) -> 0 | H36: 159 | I36: =IF(SUM(H36,F36)<0,"",SUM(H36,F36)) -> 159 | J36: =IF(G36-I36<=0,"",G36-I36) | K36: =IF(I36-G36<=0,"",I36-G36) -> 159 | N36: =IF(I36<=M36,"Reorder","Available") -> Available
B37: 100150 | C37: SF/219 Forms | D37: PCS | E37: 4225 | F37: =SUMIF(UnitsTable[Item Description],'STOCK CONTROL SHEET'!C37,UnitsTable[Running Balance]) -> 0 | G37: =IF(SUM(E37,F37)<0,"",SUM(E37,F37)) -> 4225 | H37: 4225 | I37: =IF(SUM(H37,F37)<0,"",SUM(H37,F37)) -> 4225 | J37: =IF(G37-I37<=0,"",G37-I37) | K37: =IF(I37-G37<=0,"",I37-G37) | N37: =IF(I37<=M37,"Reorder","Available") -> Available
B38: 100127 | C38: Withdrawal Ben. Folders | D38: PCS | E38: 1140 | F38: =SUMIF(UnitsTable[Item Description],'STOCK CONTROL SHEET'!C38,UnitsTable[Running Balance]) -> 0 | G38: =IF(SUM(E38,F38)<0,"",SUM(E38,F38)) -> 1140 | H38: 750 | I38: =IF(SUM(H38,F38)<0,"",SUM(H38,F38)) -> 750 | J38: =IF(G38-I38<=0,"",G38-I38) -> 390 | K38: =IF(I38-G38<=0,"",I38-G38) | L38: 15000 | M38: 5000 | N38: =IF(I38<=M38,"Reorder","Available") -> Reorder
A39: COMPUTER STORE | B39: 100172 | C39: 1 Part Statement Paper | D39: PCS | E39: 82000 | F39: =SUMIF(ComputerStoreUnitsTable[Item Description],'STOCK CONTROL SHEET'!C39,ComputerStoreUnitsTable[Running Balance]) -> -1000 | G39: =IF(SUM(E39,F39)<0,"",SUM(E39,F39)) -> 81000 | H39: 236000 | I39: =IF(SUM(H39,F39)<0,"",SUM(H39,F39)) -> 235000 | J39: =IF(G39-I39<=0,"",G39-I39) | K39: =IF(I39-G39<=0,"",I39-G39) -> 154000 | L39: 400000 | M39: 150000 | N39: =IF(I39<=M39,"Reorder","Available") -> Available
B40: 41 | C40: Tonner Kit TK-8525 (Magenta) | D40: NO | F40: =SUMIF(ComputerStoreUnitsTable[Item Description],'STOCK CONTROL SHEET'!C40,ComputerStoreUnitsTable[Running Balance]) -> 0 | G40: =IF(SUM(E40,F40)<0,"",SUM(E40,F40)) -> 0 | I40: =IF(SUM(H40,F40)<0,"",SUM(H40,F40)) -> 0 | J40: =IF(G40-I40<=0,"",G40-I40) | K40: =IF(I40-G40<=0,"",I40-G40) | N40: =IF(I40<=M40,"Reorder","Available") -> Reorder
C41: Tonner Laserjet CF350A Black | D41: NO | F41: =SUMIF(ComputerStoreUnitsTable[Item Description],'STOCK CONTROL SHEET'!C41,ComputerStoreUnitsTable[Running Balance]) -> 0 | G41: =SUM(E41,F41) -> 0 | H41: 3 | I41: =IF(SUM(H41,F41)<0,"",SUM(H41,F41)) -> 3 | J41: =IF(G41-I41<=0,"",G41-I41) | K41: =IF(I41-G41<=0,"",I41-G41) -> 3 | N41: =IF(I41<=M41,"Reorder","Available") -> Available
C42: Tonner Laserjet CF350A Yellow | D42: NO | F42: =SUMIF(ComputerStoreUnitsTable[Item Description],'STOCK CONTROL SHEET'!C42,ComputerStoreUnitsTable[Running Balance]) -> 0 | G42: =SUM(E42,F42) -> 0 | H42: 1 | I42: =IF(SUM(H42,F42)<0,"",SUM(H42,F42)) -> 1 | J42: =IF(G42-I42<=0,"",G42-I42) | K42: =IF(I42-G42<=0,"",I42-G42) -> 1 | N42: =IF(I42<=M42,"Reorder","Available") -> Available
C43: Tonner Laserjet CF350A Cyan | D43: NO | F43: =SUMIF(ComputerStoreUnitsTable[Item Description],'STOCK CONTROL SHEET'!C43,ComputerStoreUnitsTable[Running Balance]) -> 0 | G43: =SUM(E43,F43) -> 0 | H43: 5 | I43: =IF(SUM(H43,F43)<0,"",SUM(H43,F43)) -> 5 | J43: =IF(G43-I43<=0,"",G43-I43) | K43: =IF(I43-G43<=0,"",I43-G43) -> 5 | N43: =IF(I43<=M43,"Reorder","Available") -> Available
C44: Tonner Laserjet CF350A Magenta | D44: NO | F44: =SUMIF(ComputerStoreUnitsTable[Item Description],'STOCK CONTROL SHEET'!C44,ComputerStoreUnitsTable[Running Balance]) -> 0 | G44: =SUM(E44,F44) -> 0 | H44: 7 | I44: =IF(SUM(H44,F44)<0,"",SUM(H44,F44)) -> 7 | J44: =IF(G44-I44<=0,"",G44-I44) | K44: =IF(I44-G44<=0,"",I44-G44) -> 7 | N44: =IF(I44<=M44,"Reorder","Available") -> Available
C45: Tonner Laserjet 210A Cyan | D45: NO | F45: =SUMIF(ComputerStoreUnitsTable[Item Description],'STOCK CONTROL SHEET'!C45,ComputerStoreUnitsTable[Running Balance]) -> 0 | G45: =SUM(E45,F45) -> 0 | H45: 6 | I45: =IF(SUM(H45,F45)<0,"",SUM(H45,F45)) -> 6 | J45: =IF(G45-I45<=0,"",G45-I45) | K45: =IF(I45-G45<=0,"",I45-G45) -> 6 | N45: =IF(I45<=M45,"Reorder","Available") -> Available
B46: 100229 | C46: 2 PP NCR Carbonated | D46: PCS | E46: 52000 | F46: =SUMIF(ComputerStoreUnitsTable[Item Description],'STOCK CONTROL SHEET'!C46,ComputerStoreUnitsTable[Running Balance]) -> 0 | G46: =IF(SUM(E46,F46)<0,"",SUM(E46,F46)) -> 52000 | H46: 230000 | I46: =IF(SUM(H46,F46)<0,"",SUM(H46,F46)) -> 230000 | J46: =IF(G46-I46<=0,"",G46-I46) | K46: =IF(I46-G46<=0,"",I46-G46) -> 178000 | L46: 600000 | M46: 150000 | N46: =IF(I46<=M46,"Reorder","Available") -> Available
B47: 200033 | C47: Epson Ribbon 2180 | D47: PCS | E47: 51 | F47: =SUMIF(ComputerStoreUnitsTable[Item Description],'STOCK CONTROL SHEET'!C47,ComputerStoreUnitsTable[Running Balance]) -> 0 | G47: =IF(SUM(E47,F47)<0,"",SUM(E47,F47)) -> 51 | H47: 53 | I47: =IF(SUM(H47,F47)<0,"",SUM(H47,F47)) -> 53 | J47: =IF(G47-I47<=0,"",G47-I47) | K47: =IF(I47-G47<=0,"",I47-G47) -> 2 | N47: =IF(I47<=M47,"Reorder","Available") -> Available
B48: 37 | C48: Epson EB Projector/amp | D48: NO | F48: =SUMIF(ComputerStoreUnitsTable[Item Description],'STOCK CONTROL SHEET'!C48,ComputerStoreUnitsTable[Running Balance]) -> 0 | G48: =IF(SUM(E48,F48)<0,"",SUM(E48,F48)) -> 0 | I48: =IF(SUM(H48,F48)<0,"",SUM(H48,F48)) -> 0 | J48: =IF(G48-I48<=0,"",G48-I48) | K48: =IF(I48-G48<=0,"",I48-G48) | N48: =IF(I48<=M48,"Reorder","Available") -> Reorder
B49: 200033 | C49: Epson Ribbon 2190 | D49: NO | F49: =SUMIF(ComputerStoreUnitsTable[Item Description],'STOCK CONTROL SHEET'!C49,ComputerStoreUnitsTable[Running Balance]) -> 0 | G49: =SUM(E49,F49) -> 0 | H49: 11 | I49: =IF(SUM(H49,F49)<0,"",SUM(H49,F49)) -> 11 | J49: =IF(G49-I49<=0,"",G49-I49) | K49: =IF(I49-G49<=0,"",I49-G49) -> 11 | N49: =IF(I49<=M49,"Reorder","Available") -> Available
C50: Epson Ribbon LQ 675KT | D50: NO | F50: =SUMIF(ComputerStoreUnitsTable[Item Description],'STOCK CONTROL SHEET'!C50,ComputerStoreUnitsTable[Running Balance]) -> 0 | G50: =SUM(E50,F50) -> 0 | H50: 9 | I50: =IF(SUM(H50,F50)<0,"",SUM(H50,F50)) -> 9 | J50: =IF(G50-I50<=0,"",G50-I50) | K50: =IF(I50-G50<=0,"",I50-G50) -> 9 | N50: =IF(I50<=M50,"Reorder","Available") -> Available
C51: Epson Ribbon(8766) | D51: NO | F51: =SUMIF(ComputerStoreUnitsTable[Item Description],'STOCK CONTROL SHEET'!C51,ComputerStoreUnitsTable[Running Balance]) -> 0 | G51: =SUM(E51,F51) -> 0 | H51: 6 | I51: =IF(SUM(H51,F51)<0,"",SUM(H51,F51)) -> 6 | J51: =IF(G51-I51<=0,"",G51-I51) | K51: =IF(I51-G51<=0,"",I51-G51) -> 6 | N51: =IF(I51<=M51,"Reorder","Available") -> Available
C52: Tally Ribbon T2130 | D52: NO | F52: =SUMIF(ComputerStoreUnitsTable[Item Description],'STOCK CONTROL SHEET'!C52,ComputerStoreUnitsTable[Running Balance]) -> 0 | G52: =SUM(E52,F52) -> 0 | H52: 19 | I52: =IF(SUM(H52,F52)<0,"",SUM(H52,F52)) -> 19 | J52: =IF(G52-I52<=0,"",G52-I52) | K52: =IF(I52-G52<=0,"",I52-G52) -> 19 | N52: =IF(I52<=M52,"Reorder","Available") -> Available
B53: 200024 | C53: Epson DFX 5000 Ribbon(8766) | D53: PCS | F53: =SUMIF(ComputerStoreUnitsTable[Item Description],'STOCK CONTROL SHEET'!C53,ComputerStoreUnitsTable[Running Balance]) -> 0 | G53: =IF(SUM(E53,F53)<0,"",SUM(E53,F53)) -> 0 | H53: 7 | I53: =IF(SUM(H53,F53)<0,"",SUM(H53,F53)) -> 7 | J53: =IF(G53-I53<=0,"",G53-I53) | K53: =IF(I53-G53<=0,"",I53-G53) -> 7 | N53: =IF(I53<=M53,"Reorder","Available") -> Available
B54: 200031 | C54: Epson Ribbon LX 300 (8750) | D54: NO | F54: =SUMIF(ComputerStoreUnitsTable[Item Description],'STOCK CONTROL SHEET'!C54,ComputerStoreUnitsTable[Running Balance]) -> 0 | G54: =IF(SUM(E54,F54)<0,"",SUM(E54,F54)) -> 0 | H54: 5 | I54: =IF(SUM(H54,F54)<0,"",SUM(H54,F54)) -> 5 | J54: =IF(G54-I54<=0,"",G54-I54) | K54: =IF(I54-G54<=0,"",I54-G54) -> 5 | L54: 6 | M54: 2 | N54: =IF(I54<=M54,"Reorder","Available") -> Available
C55: Epson Ribbon ERC 31P | D55: NO | F55: =SUMIF(ComputerStoreUnitsTable[Item Description],'STOCK CONTROL SHEET'!C55,ComputerStoreUnitsTable[Running Balance]) -> 0 | G55: =SUM(E55,F55) -> 0 | H55: 1 | I55: =IF(SUM(H55,F55)<0,"",SUM(H55,F55)) -> 1 | J55: =IF(G55-I55<=0,"",G55-I55) | K55: =IF(I55-G55<=0,"",I55-G55) -> 1 | N55: =IF(I55<=M55,"Reorder","Available") -> Available
B56: 200030 | C56: Epson DFX 9000 | D56: NO | F56: =SUMIF(ComputerStoreUnitsTable[Item Description],'STOCK CONTROL SHEET'!C56,ComputerStoreUnitsTable[Running Balance]) -> 0 | G56: =IF(SUM(E56,F56)<0,"",SUM(E56,F56)) -> 0 | H56: 8 | I56: =IF(SUM(H56,F56)<0,"",SUM(H56,F56)) -> 8 | J56: =IF(G56-I56<=0,"",G56-I56) | K56: =IF(I56-G56<=0,"",I56-G56) -> 8 | N56: =IF(I56<=M56,"Reorder","Available") -> Available
B57: 200067 | C57: Epson Ribbon LQ 690 (Black) | D57: NO | E57: 23 | F57: =SUMIF(ComputerStoreUnitsTable[Item Description],'STOCK CONTROL SHEET'!C57,ComputerStoreUnitsTable[Running Balance]) -> 0 | G57: =IF(SUM(E57,F57)<0,"",SUM(E57,F57)) -> 23 | H57: 0 | I57: =IF(SUM(H57,F57)<0,"",SUM(H57,F57)) -> 0 | J57: =IF(G57-I57<=0,"",G57-I57) -> 23 | K57: =IF(I57-G57<=0,"",I57-G57) | L57: 40 | M57: 9 | N57: =IF(I57<=M57,"Reorder","Available") -> Reorder
B58: 200034 | C58: Epson Ribbon LX 2090 FX | D58: NO | F58: =SUMIF(ComputerStoreUnitsTable[Item Description],'STOCK CONTROL SHEET'!C58,ComputerStoreUnitsTable[Running Balance]) -> 0 | G58: =IF(SUM(E58,F58)<0,"",SUM(E58,F58)) -> 0 | I58: =IF(SUM(H58,F58)<0,"",SUM(H58,F58)) -> 0 | J58: =IF(G58-I58<=0,"",G58-I58) | K58: =IF(I58-G58<=0,"",I58-G58) | N58: =IF(I58<=M58,"Reorder","Available") -> Reorder
B59: 200070 | C59: HP Laserjet Tonner 237A Black | D59: NO | F59: =SUMIF(ComputerStoreUnitsTable[Item Description],'STOCK CONTROL SHEET'!C59,ComputerStoreUnitsTable[Running Balance]) -> 0 | G59: =IF(SUM(E59,F59)<0,"",SUM(E59,F59)) -> 0 | H59: 14 | I59: =IF(SUM(H59,F59)<0,"",SUM(H59,F59)) -> 14 | J59: =IF(G59-I59<=0,"",G59-I59) | K59: =IF(I59-G59<=0,"",I59-G59) -> 14 | L59: 30 | M59: 8 | N59: =IF(I59<=M59,"Reorder","Available") -> Available
B60: 200066 | C60: HP Laserjet Tonner 130A (Magenta) | D60: NO | F60: =SUMIF(ComputerStoreUnitsTable[Item Description],'STOCK CONTROL SHEET'!C60,ComputerStoreUnitsTable[Running Balance]) -> 0 | G60: =IF(SUM(E60,F60)<0,"",SUM(E60,F60)) -> 0 | I60: =IF(SUM(H60,F60)<0,"",SUM(H60,F60)) -> 0 | J60: =IF(G60-I60<=0,"",G60-I60) | K60: =IF(I60-G60<=0,"",I60-G60) | L60: 6 | M60: 1 | N60: =IF(I60<=M60,"Reorder","Available") -> Reorder
C61: HP Laserjet 4600N Tonner (9723A) (Cyan) | D61: NO | F61: =SUMIF(ComputerStoreUnitsTable[Item Description],'STOCK CONTROL SHEET'!C61,ComputerStoreUnitsTable[Running Balance]) -> 0 | G61: =SUM(E61,F61) -> 0 | H61: 3 | I61: =IF(SUM(H61,F61)<0,"",SUM(H61,F61)) -> 3 | J61: =IF(G61-I61<=0,"",G61-I61) | K61: =IF(I61-G61<=0,"",I61-G61) -> 3 | N61: =IF(I61<=M61,"Reorder","Available") -> Available
B62: 200007 | C62: HP Laserjet 4600N Tonner (9723A) (Magenta) | D62: NO | F62: =SUMIF(ComputerStoreUnitsTable[Item Description],'STOCK CONTROL SHEET'!C62,ComputerStoreUnitsTable[Running Balance]) -> 0 | G62: =IF(SUM(E62,F62)<0,"",SUM(E62,F62)) -> 0 | I62: =IF(SUM(H62,F62)<0,"",SUM(H62,F62)) -> 0 | J62: =IF(G62-I62<=0,"",G62-I62) | K62: =IF(I62-G62<=0,"",I62-G62) | N62: =IF(I62<=M62,"Reorder","Available") -> Reorder
B63: 200076 | C63: HP Laserjet Tonner CF 541A (Cyan) | D63: NO | F63: =SUMIF(ComputerStoreUnitsTable[Item Description],'STOCK CONTROL SHEET'!C63,ComputerStoreUnitsTable[Running Balance]) -> 0 | G63: =IF(SUM(E63,F63)<0,"",SUM(E63,F63)) -> 0 | I63: =IF(SUM(H63,F63)<0,"",SUM(H63,F63)) -> 0 | J63: =IF(G63-I63<=0,"",G63-I63) | K63: =IF(I63-G63<=0,"",I63-G63) | L63: 12 | M63: 2 | N63: =IF(I63<=M63,"Reorder","Available") -> Reorder
B64: 200072 | C64: HP Laserjet Tonner CF 226A | D64: NO | F64: =SUMIF(ComputerStoreUnitsTable[Item Description],'STOCK CONTROL SHEET'!C64,ComputerStoreUnitsTable[Running Balance]) -> 0 | G64: =IF(SUM(E64,F64)<0,"",SUM(E64,F64)) -> 0 | I64: =IF(SUM(H64,F64)<0,"",SUM(H64,F64)) -> 0 | J64: =IF(G64-I64<=0,"",G64-I64) | K64: =IF(I64-G64<=0,"",I64-G64) | L64: 4 | M64: 1 | N64: =IF(I64<=M64,"Reorder","Available") -> Reorder
B65: 200059 | C65: HP Laserjet Tonner 402A (Yellow) | D65: NO | E65: 4 | F65: =SUMIF(ComputerStoreUnitsTable[Item Description],'STOCK CONTROL SHEET'!C65,ComputerStoreUnitsTable[Running Balance]) -> 0 | G65: =IF(SUM(E65,F65)<0,"",SUM(E65,F65)) -> 4 | H65: 4 | I65: =IF(SUM(H65,F65)<0,"",SUM(H65,F65)) -> 4 | J65: =IF(G65-I65<=0,"",G65-I65) | K65: =IF(I65-G65<=0,"",I65-G65) | L65: 6 | M65: 2 | N65: =IF(I65<=M65,"Reorder","Available") -> Available
B66: 200056 | C66: HP Laserjet Tonner 400A (Black) | D66: NO | E66: 7 | F66: =SUMIF(ComputerStoreUnitsTable[Item Description],'STOCK CONTROL SHEET'!C66,ComputerStoreUnitsTable[Running Balance]) -> 0 | G66: =IF(SUM(E66,F66)<0,"",SUM(E66,F66)) -> 7 | H66: 7 | I66: =IF(SUM(H66,F66)<0,"",SUM(H66,F66)) -> 7 | J66: =IF(G66-I66<=0,"",G66-I66) | K66: =IF(I66-G66<=0,"",I66-G66) | L66: 6 | M66: 2 | N66: =IF(I66<=M66,"Reorder","Available") -> Available
B67: 200065 | C67: HP Laserjet Tonner 130A (Yellow) | D67: NO | F67: =SUMIF(ComputerStoreUnitsTable[Item Description],'STOCK CONTROL SHEET'!C67,ComputerStoreUnitsTable[Running Balance]) -> 0 | G67: =IF(SUM(E67,F67)<0,"",SUM(E67,F67)) -> 0 | I67: =IF(SUM(H67,F67)<0,"",SUM(H67,F67)) -> 0 | J67: =IF(G67-I67<=0,"",G67-I67) | K67: =IF(I67-G67<=0,"",I67-G67) | L67: 4 | M67: 1 | N67: =IF(I67<=M67,"Reorder","Available") -> Reorder
B68: 200075 | C68: HP Laserjet Tonner CF 540A (Black) | D68: NO | F68: =SUMIF(ComputerStoreUnitsTable[Item Description],'STOCK CONTROL SHEET'!C68,ComputerStoreUnitsTable[Running Balance]) -> 0 | G68: =IF(SUM(E68,F68)<0,"",SUM(E68,F68)) -> 0 | I68: =IF(SUM(H68,F68)<0,"",SUM(H68,F68)) -> 0 | J68: =IF(G68-I68<=0,"",G68-I68) | K68: =IF(I68-G68<=0,"",I68-G68) | L68: 6 | M68: 3 | N68: =IF(I68<=M68,"Reorder","Available") -> Reorder
B69: 200073 | C69: HP Laserjet Tonner CF 287A | D69: NO | E69: 4 | F69: =SUMIF(ComputerStoreUnitsTable[Item Description],'STOCK CONTROL SHEET'!C69,ComputerStoreUnitsTable[Running Balance]) -> 0 | G69: =IF(SUM(E69,F69)<0,"",SUM(E69,F69)) -> 4 | H69: 5 | I69: =IF(SUM(H69,F69)<0,"",SUM(H69,F69)) -> 5 | J69: =IF(G69-I69<=0,"",G69-I69) | K69: =IF(I69-G69<=0,"",I69-G69) -> 1 | L69: 4 | M69: 2 | N69: =IF(I69<=M69,"Reorder","Available") -> Available
B70: 200064 | C70: HP Laserjet Tonner 130A (Cyan) | D70: NO | F70: =SUMIF(ComputerStoreUnitsTable[Item Description],'STOCK CONTROL SHEET'!C70,ComputerStoreUnitsTable[Running Balance]) -> 0 | G70: =IF(SUM(E70,F70)<0,"",SUM(E70,F70)) -> 0 | I70: =IF(SUM(H70,F70)<0,"",SUM(H70,F70)) -> 0 | J70: =IF(G70-I70<=0,"",G70-I70) | K70: =IF(I70-G70<=0,"",I70-G70) | L70: 6 | M70: 1 | N70: =IF(I70<=M70,"Reorder","Available") -> Reorder
B71: 200063 | C71: HP Laserjet Tonner 130A (Black) | D71: NO | F71: =SUMIF(ComputerStoreUnitsTable[Item Description],'STOCK CONTROL SHEET'!C71,ComputerStoreUnitsTable[Running Balance]) -> 0 | G71: =IF(SUM(E71,F71)<0,"",SUM(E71,F71)) -> 0 | I71: =IF(SUM(H71,F71)<0,"",SUM(H71,F71)) -> 0 | J71: =IF(G71-I71<=0,"",G71-I71) | K71: =IF(I71-G71<=0,"",I71-G71) | L71: 6 | M71: 1 | N71: =IF(I71<=M71,"Reorder","Available") -> Reorder
C72: HP Laserjet 4600N Tonner (9721A) Cyan | D72: NO | F72: =SUMIF(ComputerStoreUnitsTable[Item Description],'STOCK CONTROL SHEET'!C72,ComputerStoreUnitsTable[Running Balance]) -> 0 | G72: =SUM(E72,F72) -> 0 | H72: 3 | I72: =IF(SUM(H72,F72)<0,"",SUM(H72,F72)) -> 3 | J72: =IF(G72-I72<=0,"",G72-I72) | K72: =IF(I72-G72<=0,"",I72-G72) -> 3 | N72: =IF(I72<=M72,"Reorder","Available") -> Available
B73: 200009 | C73: HP Laserjet 4600N Tonner (9721A) Blue | D73: NO | F73: =SUMIF(ComputerStoreUnitsTable[Item Description],'STOCK CONTROL SHEET'!C73,ComputerStoreUnitsTable[Running Balance]) -> 0 | G73: =IF(SUM(E73,F73)<0,"",SUM(E73,F73)) -> 0 | I73: =IF(SUM(H73,F73)<0,"",SUM(H73,F73)) -> 0 | J73: =IF(G73-I73<=0,"",G73-I73) | K73: =IF(I73-G73<=0,"",I73-G73) | N73: =IF(I73<=M73,"Reorder","Available") -> Reorder
C74: HP Laserjet 4600N Tonner (9720A) Yellow | D74: NO | F74: =SUMIF(ComputerStoreUnitsTable[Item Description],'STOCK CONTROL SHEET'!C74,ComputerStoreUnitsTable[Running Balance]) -> 0 | G74: =SUM(E74,F74) -> 0 | H74: 4 | I74: =IF(SUM(H74,F74)<0,"",SUM(H74,F74)) -> 4 | J74: =IF(G74-I74<=0,"",G74-I74) | K74: =IF(I74-G74<=0,"",I74-G74) -> 4 | N74: =IF(I74<=M74,"Reorder","Available") -> Available
B75: 200010 | C75: HP Laserjet 4600N Tonner (9720A) Black | D75: NO | F75: =SUMIF(ComputerStoreUnitsTable[Item Description],'STOCK CONTROL SHEET'!C75,ComputerStoreUnitsTable[Running Balance]) -> 0 | G75: =IF(SUM(E75,F75)<0,"",SUM(E75,F75)) -> 0 | H75: 8 | I75: =IF(SUM(H75,F75)<0,"",SUM(H75,F75)) -> 8 | J75: =IF(G75-I75<=0,"",G75-I75) | K75: =IF(I75-G75<=0,"",I75-G75) -> 8 | N75: =IF(I75<=M75,"Reorder","Available") -> Available
B76: 200000 | C76: HP Laserjet Tonner (9722A) Yellow | D76: NO | F76: =SUMIF(ComputerStoreUnitsTable[Item Description],'STOCK CONTROL SHEET'!C76,ComputerStoreUnitsTable[Running Balance]) -> 0 | G76: =IF(SUM(E76,F76)<0,"",SUM(E76,F76)) -> 0 | I76: =IF(SUM(H76,F76)<0,"",SUM(H76,F76)) -> 0 | J76: =IF(G76-I76<=0,"",G76-I76) | K76: =IF(I76-G76<=0,"",I76-G76) | N76: =IF(I76<=M76,"Reorder","Available") -> Reorder
B77: 200079 | C77: HP Laserjet Tonner 543A (Magenta) | D77: NO | F77: =SUMIF(ComputerStoreUnitsTable[Item Description],'STOCK CONTROL SHEET'!C77,ComputerStoreUnitsTable[Running Balance]) -> 0 | G77: =IF(SUM(E77,F77)<0,"",SUM(E77,F77)) -> 0 | I77: =IF(SUM(H77,F77)<0,"",SUM(H77,F77)) -> 0 | J77: =IF(G77-I77<=0,"",G77-I77) | K77: =IF(I77-G77<=0,"",I77-G77) | L77: 12 | M77: 2 | N77: =IF(I77<=M77,"Reorder","Available") -> Reorder
B78: 200008 | C78: HP Laserjet Tonner 2550 Q3964A (Color) | D78: NO | F78: =SUMIF(ComputerStoreUnitsTable[Item Description],'STOCK CONTROL SHEET'!C78,ComputerStoreUnitsTable[Running Balance]) -> 0 | G78: =IF(SUM(E78,F78)<0,"",SUM(E78,F78)) -> 0 | H78: 1 | I78: =IF(SUM(H78,F78)<0,"",SUM(H78,F78)) -> 1 | J78: =IF(G78-I78<=0,"",G78-I78) | K78: =IF(I78-G78<=0,"",I78-G78) -> 1 | N78: =IF(I78<=M78,"Reorder","Available") -> Available
B79: 200017 | C79: Lex Mark C920 Ribbon Magenta | D79: NO | F79: =SUMIF(ComputerStoreUnitsTable[Item Description],'STOCK CONTROL SHEET'!C79,ComputerStoreUnitsTable[Running Balance]) -> 0 | G79: =IF(SUM(E79,F79)<0,"",SUM(E79,F79)) -> 0 | H79: 3 | I79: =IF(SUM(H79,F79)<0,"",SUM(H79,F79)) -> 3 | J79: =IF(G79-I79<=0,"",G79-I79) | K79: =IF(I79-G79<=0,"",I79-G79) -> 3 | N79: =IF(I79<=M79,"Reorder","Available") -> Available
B80: 200028 | C80: Lex Mark C920 Ribbon Black | D80: NO | F80: =SUMIF(ComputerStoreUnitsTable[Item Description],'STOCK CONTROL SHEET'!C80,ComputerStoreUnitsTable[Running Balance]) -> 0 | G80: =IF(SUM(E80,F80)<0,"",SUM(E80,F80)) -> 0 | H80: 2 | I80: =IF(SUM(H80,F80)<0,"",SUM(H80,F80)) -> 2 | J80: =IF(G80-I80<=0,"",G80-I80) | K80: =IF(I80-G80<=0,"",I80-G80) -> 2 | N80: =IF(I80<=M80,"Reorder","Available") -> Available
B81: 200029 | C81: Lex Mark C920 Yellow | D81: NO | F81: =SUMIF(ComputerStoreUnitsTable[Item Description],'STOCK CONTROL SHEET'!C81,ComputerStoreUnitsTable[Running Balance]) -> 0 | G81: =IF(SUM(E81,F81)<0,"",SUM(E81,F81)) -> 0 | H81: 4 | I81: =IF(SUM(H81,F81)<0,"",SUM(H81,F81)) -> 4 | J81: =IF(G81-I81<=0,"",G81-I81) | K81: =IF(I81-G81<=0,"",I81-G81) -> 4 | N81: =IF(I81<=M81,"Reorder","Available") -> Available
C82: Epson Ribbon LQ 590 | D82: NO | E82: 0 | F82: =SUMIF(ComputerStoreUnitsTable[Item Description],'STOCK CONTROL SHEET'!C82,ComputerStoreUnitsTable[Running Balance]) -> 0 | G82: =SUM(E82,F82) -> 0 | H82: 3 | I82: =IF(SUM(H82,F82)<0,"",SUM(H82,F82)) -> 3 | J82: =IF(G82-I82<=0,"",G82-I82) | K82: =IF(I82-G82<=0,"",I82-G82) -> 3 | N82: =IF(I82<=M82,"Reorder","Available") -> Available
B83: 38 | C83: Tonner Laser Jet 2550 LQ 3971A | D83: EA | F83: =SUMIF(ComputerStoreUnitsTable[Item Description],'STOCK CONTROL SHEET'!C83,ComputerStoreUnitsTable[Running Balance]) -> 0 | G83: =IF(SUM(E83,F83)<0,"",SUM(E83,F83)) -> 0 | I83: =IF(SUM(H83,F83)<0,"",SUM(H83,F83)) -> 0 | J83: =IF(G83-I83<=0,"",G83-I83) | K83: =IF(I83-G83<=0,"",I83-G83) | L83: 5 | M83: 2 | N83: =IF(I83<=M83,"Reorder","Available") -> Reorder
B84: 200001 | C84: HP Laserjet Tonner 2550L Q3960A | D84: NO | F84: =SUMIF(ComputerStoreUnitsTable[Item Description],'STOCK CONTROL SHEET'!C84,ComputerStoreUnitsTable[Running Balance]) -> 0 | G84: =IF(SUM(E84,F84)<0,"",SUM(E84,F84)) -> 0 | H84: 4 | I84: =IF(SUM(H84,F84)<0,"",SUM(H84,F84)) -> 4 | J84: =IF(G84-I84<=0,"",G84-I84) | K84: =IF(I84-G84<=0,"",I84-G84) -> 4 | N84: =IF(I84<=M84,"Reorder","Available") -> Available
B85: 200091 | C85: Kyocera Ecosys 3060-9X4BO47 | D85: NO | E85: 16 | F85: =SUMIF(ComputerStoreUnitsTable[Item Description],'STOCK CONTROL SHEET'!C85,ComputerStoreUnitsTable[Running Balance]) -> 0 | G85: =IF(SUM(E85,F85)<0,"",SUM(E85,F85)) -> 16 | H85: 15 | I85: =IF(SUM(H85,F85)<0,"",SUM(H85,F85)) -> 15 | J85: =IF(G85-I85<=0,"",G85-I85) -> 1 | K85: =IF(I85-G85<=0,"",I85-G85) | N85: =IF(I85<=M85,"Reorder","Available") -> Available
B86: 100170 | C86: 1 Part Plain Paper 9(1/2) * 11 | D86: NO | E86: 16000 | F86: =SUMIF(ComputerStoreUnitsTable[Item Description],'STOCK CONTROL SHEET'!C86,ComputerStoreUnitsTable[Running Balance]) -> 0 | G86: =IF(SUM(E86,F86)<0,"",SUM(E86,F86)) -> 16000 | H86: 26000 | I86: =IF(SUM(H86,F86)<0,"",SUM(H86,F86)) -> 26000 | J86: =IF(G86-I86<=0,"",G86-I86) | K86: =IF(I86-G86<=0,"",I86-G86) -> 10000 | L86: 36000 | M86: 9000 | N86: =IF(I86<=M86,"Reorder","Available") -> Available
B87: 200100 | C87: HP Laserjet Tonner 230A (Magenta) | D87: NO | E87: 8 | F87: =SUMIF(ComputerStoreUnitsTable[Item Description],'STOCK CONTROL SHEET'!C87,ComputerStoreUnitsTable[Running Balance]) -> 0 | G87: =SUM(E87,F87) -> 8 | H87: 4 | I87: =IF(SUM(H87,F87)<0,"",SUM(H87,F87)) -> 4 | J87: =IF(G87-I87<=0,"",G87-I87) -> 4 | K87: =IF(I87-G87<=0,"",I87-G87) | N87: =IF(I87<=M87,"Reorder","Available") -> Available
B88: 200098 | C88: HP Laserjet Tonner 230A (Yellow) | D88: NO | E88: 8 | F88: =SUMIF(ComputerStoreUnitsTable[Item Description],'STOCK CONTROL SHEET'!C88,ComputerStoreUnitsTable[Running Balance]) -> 0 | G88: =SUM(E88,F88) -> 8 | H88: 5 | I88: =IF(SUM(H88,F88)<0,"",SUM(H88,F88)) -> 5 | J88: =IF(G88-I88<=0,"",G88-I88) -> 3 | K88: =IF(I88-G88<=0,"",I88-G88) | N88: =IF(I88<=M88,"Reorder","Available") -> Available
B89: 200097 | C89: HP Laserjet Tonner 230A (BLACK) | D89: NO | E89: 27 | F89: =SUMIF(ComputerStoreUnitsTable[Item Description],'STOCK CONTROL SHEET'!C89,ComputerStoreUnitsTable[Running Balance]) -> 0 | G89: =SUM(E89,F89) -> 27 | H89: 24 | I89: =IF(SUM(H89,F89)<0,"",SUM(H89,F89)) -> 24 | J89: =IF(G89-I89<=0,"",G89-I89) -> 3 | K89: =IF(I89-G89<=0,"",I89-G89) | N89: =IF(I89<=M89,"Reorder","Available") -> Available
B90: 200099 | C90: HP Laserjet Tonner 230A (Cyan) | D90: NO | E90: 8 | F90: =SUMIF(ComputerStoreUnitsTable[Item Description],'STOCK CONTROL SHEET'!C90,ComputerStoreUnitsTable[Running Balance]) -> 0 | G90: =SUM(E90,F90) -> 8 | H90: 5 | I90: =IF(SUM(H90,F90)<0,"",SUM(H90,F90)) -> 5 | J90: =IF(G90-I90<=0,"",G90-I90) -> 3 | K90: =IF(I90-G90<=0,"",I90-G90) | N90: =IF(I90<=M90,"Reorder","Available") -> Available
B91: 200051 | C91: Toner HP 2612 A Black-HP3015 | D91: NO | F91: =SUMIF(ComputerStoreUnitsTable[Item Description],'STOCK CONTROL SHEET'!C91,ComputerStoreUnitsTable[Running Balance]) -> 0 | G91: =IF(SUM(E91,F91)<0,"",SUM(E91,F91)) -> 0 | H91: 1 | I91: =IF(SUM(H91,F91)<0,"",SUM(H91,F91)) -> 1 | J91: =IF(G91-I91<=0,"",G91-I91) | K91: =IF(I91-G91<=0,"",I91-G91) -> 1 | N91: =IF(I91<=M91,"Reorder","Available") -> Available
B92: 200002 | C92: HP Laserjet Tonner C920 Cyan | D92: NO | F92: =SUMIF(ComputerStoreUnitsTable[Item Description],'STOCK CONTROL SHEET'!C92,ComputerStoreUnitsTable[Running Balance]) -> 0 | G92: =IF(SUM(E92,F92)<0,"",SUM(E92,F92)) -> 0 | H92: 5 | I92: =IF(SUM(H92,F92)<0,"",SUM(H92,F92)) -> 5 | J92: =IF(G92-I92<=0,"",G92-I92) | K92: =IF(I92-G92<=0,"",I92-G92) -> 5 | N92: =IF(I92<=M92,"Reorder","Available") -> Available
B93: 200069 | C93: Toner Hp Laserjet CF281A | D93: EA | E93: 22 | F93: =SUMIF(ComputerStoreUnitsTable[Item Description],'STOCK CONTROL SHEET'!C93,ComputerStoreUnitsTable[Running Balance]) -> 0 | G93: =IF(SUM(E93,F93)<0,"",SUM(E93,F93)) -> 22 | H93: 19 | I93: =IF(SUM(H93,F93)<0,"",SUM(H93,F93)) -> 19 | J93: =IF(G93-I93<=0,"",G93-I93) -> 3 | K93: =IF(I93-G93<=0,"",I93-G93) | L93: 5 | M93: 3 | N93: =IF(I93<=M93,"Reorder","Available") -> Available
C94: HP Laserjet Tonner Q 3972A Magenta | D94: NO | F94: =SUMIF(ComputerStoreUnitsTable[Item Description],'STOCK CONTROL SHEET'!C94,ComputerStoreUnitsTable[Running Balance]) -> 0 | G94: =SUM(E94,F94) -> 0 | H94: 1 | I94: =IF(SUM(H94,F94)<0,"",SUM(H94,F94)) -> 1 | J94: =IF(G94-I94<=0,"",G94-I94) | K94: =IF(I94-G94<=0,"",I94-G94) -> 1 | N94: =IF(I94<=M94,"Reorder","Available") -> Available
B95: 200016 | C95: HP Laserjet Tonner 3972 A (Yellow) | D95: NO | F95: =SUMIF(ComputerStoreUnitsTable[Item Description],'STOCK CONTROL SHEET'!C95,ComputerStoreUnitsTable[Running Balance]) -> 0 | G95: =IF(SUM(E95,F95)<0,"",SUM(E95,F95)) -> 0 | H95: 2 | I95: =IF(SUM(H95,F95)<0,"",SUM(H95,F95)) -> 2 | J95: =IF(G95-I95<=0,"",G95-I95) | K95: =IF(I95-G95<=0,"",I95-G95) -> 2 | L95: 5 | M95: 2 | N95: =IF(I95<=M95,"Reorder","Available") -> Reorder
B96: 200011 | C96: HP Laserjet Tonner 4000T CF4127X (4050N) | D96: NO | F96: =SUMIF(ComputerStoreUnitsTable[Item Description],'STOCK CONTROL SHEET'!C96,ComputerStoreUnitsTable[Running Balance]) -> 0 | G96: =IF(SUM(E96,F96)<0,"",SUM(E96,F96)) -> 0 | H96: 4 | I96: =IF(SUM(H96,F96)<0,"",SUM(H96,F96)) -> 4 | J96: =IF(G96-I96<=0,"",G96-I96) | K96: =IF(I96-G96<=0,"",I96-G96) -> 4 | L96: 5 | M96: 3 | N96: =IF(I96<=M96,"Reorder","Available") -> Available
B97: 100237 | C97: Toner HP 59A Black (259A) | D97: NO | F97: =SUMIF(ComputerStoreUnitsTable[Item Description],'STOCK CONTROL SHEET'!C97,ComputerStoreUnitsTable[Running Balance]) -> 0 | G97: =IF(SUM(E97,F97)<0,"",SUM(E97,F97)) -> 0 | I97: =IF(SUM(H97,F97)<0,"",SUM(H97,F97)) -> 0 | J97: =IF(G97-I97<=0,"",G97-I97) | K97: =IF(I97-G97<=0,"",I97-G97) | N97: =IF(I97<=M97,"Reorder","Available") -> Reorder
B98: 200089 | C98: Tonner Kyocera 4053A (Magenta) 8517m | D98: NO | E98: 3 | F98: =SUMIF(ComputerStoreUnitsTable[Item Description],'STOCK CONTROL SHEET'!C98,ComputerStoreUnitsTable[Running Balance]) -> 0 | G98: =IF(SUM(E98,F98)<0,"",SUM(E98,F98)) -> 3 | H98: 4 | I98: =IF(SUM(H98,F98)<0,"",SUM(H98,F98)) -> 4 | J98: =IF(G98-I98<=0,"",G98-I98) | K98: =IF(I98-G98<=0,"",I98-G98) -> 1 | L98: 5 | M98: 2 | N98: =IF(I98<=M98,"Reorder","Available") -> Available
B99: 200019 | C99: Tonner CE 390A | D99: NO | E99: 11 | F99: =SUMIF(ComputerStoreUnitsTable[Item Description],'STOCK CONTROL SHEET'!C99,ComputerStoreUnitsTable[Running Balance]) -> 0 | G99: =IF(SUM(E99,F99)<0,"",SUM(E99,F99)) -> 11 | H99: 9 | I99: =IF(SUM(H99,F99)<0,"",SUM(H99,F99)) -> 9 | J99: =IF(G99-I99<=0,"",G99-I99) -> 2 | K99: =IF(I99-G99<=0,"",I99-G99) | L99: 12 | M99: 4 | N99: =IF(I99<=M99,"Reorder","Available") -> Available
B100: 200015 | C100: Toner Cartridge HP C8543X (9040N) | D100: NO | F100: =SUMIF(ComputerStoreUnitsTable[Item Description],'STOCK CONTROL SHEET'!C100,ComputerStoreUnitsTable[Running Balance]) -> 0 | G100: =IF(SUM(E100,F100)<0,"",SUM(E100,F100)) -> 0 | I100: =IF(SUM(H100,F100)<0,"",SUM(H100,F100)) -> 0 | J100: =IF(G100-I100<=0,"",G100-I100) | K100: =IF(I100-G100<=0,"",I100-G100) | N100: =IF(I100<=M100,"Reorder","Available") -> Reorder
B101: 200085 | C101: Tonner TK 8515 (Cyan) 5053 | D101: NO | E101: 6 | F101: =SUMIF(ComputerStoreUnitsTable[Item Description],'STOCK CONTROL SHEET'!C101,ComputerStoreUnitsTable[Running Balance]) -> 0 | G101: =IF(SUM(E101,F101)<0,"",SUM(E101,F101)) -> 6 | H101: 8 | I101: =IF(SUM(H101,F101)<0,"",SUM(H101,F101)) -> 8 | J101: =IF(G101-I101<=0,"",G101-I101) | K101: =IF(I101-G101<=0,"",I101-G101) -> 2 | L101: 5 | M101: 2 | N101: =IF(I101<=M101,"Reorder","Available") -> Available
B102: 200083 | C102: Tonner 8515TK (Yellow) 5053 | D102: NO | E102: 6 | F102: =SUMIF(ComputerStoreUnitsTable[Item Description],'STOCK CONTROL SHEET'!C102,ComputerStoreUnitsTable[Running Balance]) -> 0 | G102: =IF(SUM(E102,F102)<0,"",SUM(E102,F102)) -> 6 | H102: 8 | I102: =IF(SUM(H102,F102)<0,"",SUM(H102,F102)) -> 8 | J102: =IF(G102-I102<=0,"",G102-I102) | K102: =IF(I102-G102<=0,"",I102-G102) -> 2 | L102: 5 | M102: 2 | N102: =IF(I102<=M102,"Reorder","Available") -> Available
...

Sheet INVENTORY STATUS
A1: LIVE TRACKING UPDATE OF STOCK STATUS PER STORE
A2: Current Inventory | F2: STORE | G2: Inventory Status
A3: Material No | B3: Item Description | C3: Unit Of Issue | D3: Reorder Levels | E3: Quantity | G3: Material No | H3: In Stock | I3: Out of Stock
A4: =SFMaterialNo -> 282014 | B4: =IF(A4="","",VLOOKUP(A4,SF.STOREPRIMARY[],2,FALSE)) -> Tissue Papers | C4: =IF(A4="","",VLOOKUP(A4,'STOCK CONTROL SHEET'!Details,3,FALSE)) -> ROLL | D4: =SF.STOREPRIMARY[Reorder Levels] -> 500 | E4: =SF.STOREPRIMARY[Physical Stock Bal.] -> 0 | F4: SF STORE | G4: =SFMaterialNo -> 282014 | H4: =IF(Table2[[#This Row],[Quantity]]>Table2[[#This Row],[Reorder Levels]],Table2[Item Description],"") | I4: =IF(Table2[[#This Row],[Quantity]]<=Table2[[#This Row],[Reorder Levels]],Table2[Item Description],"") -> Tissue Papers
A5: =SFMaterialNo -> 100126 | B5: =IF(A5="","",VLOOKUP(A5,SF.STOREPRIMARY[],2,FALSE)) -> Administration Folders | C5: =IF(A5="","",VLOOKUP(A5,'STOCK CONTROL SHEET'!Details,3,FALSE)) -> PCS | D5: =SF.STOREPRIMARY[Reorder Levels] -> 450 | E5: =SF.STOREPRIMARY[Physical Stock Bal.] -> 0 | G5: =SFMaterialNo -> 100126 | H5: =IF(Table2[[#This Row],[Quantity]]>Table2[[#This Row],[Reorder Levels]],Table2[Item Description],"") | I5: =IF(Table2[[#This Row],[Quantity]]<=Table2[[#This Row],[Reorder Levels]],Table2[Item Description],"") -> Administration Folders
A6: =SFMaterialNo -> 100128 | B6: =IF(A6="","",VLOOKUP(A6,SF.STOREPRIMARY[],2,FALSE)) -> Age Benefit Folders | C6: =IF(A6="","",VLOOKUP(A6,'STOCK CONTROL SHEET'!Details,3,FALSE)) -> PCS | D6: =SF.STOREPRIMARY[Reorder Levels] -> 4500 | E6: =SF.STOREPRIMARY[Physical Stock Bal.] -> 176 | G6: =SFMaterialNo -> 100128 | H6: =IF(Table2[[#This Row],[Quantity]]>Table2[[#This Row],[Reorder Levels]],Table2[Item Description],"") | I6: =IF(Table2[[#This Row],[Quantity]]<=Table2[[#This Row],[Reorder Levels]],Table2[Item Description],"") -> Age Benefit Folders
A7: =SFMaterialNo -> 100216 | B7: =IF(A7="","",VLOOKUP(A7,SF.STOREPRIMARY[],2,FALSE)) -> App. For Personal Exemption Forms | C7: =IF(A7="","",VLOOKUP(A7,'STOCK CONTROL SHEET'!Details,3,FALSE)) -> PCS | D7: =SF.STOREPRIMARY[Reorder Levels] -> 3000 | E7: =SF.STOREPRIMARY[Physical Stock Bal.] -> 0 | G7: =SFMaterialNo -> 100216 | H7: =IF(Table2[[#This Row],[Quantity]]>Table2[[#This Row],[Reorder Levels]],Table2[Item Description],"") | I7: =IF(Table2[[#This Row],[Quantity]]<=Table2[[#This Row],[Reorder Levels]],Table2[Item Description],"") -> App. For Personal Exemption Forms
A8: =SFMaterialNo -> 100139 | B8: =IF(A8="","",VLOOKUP(A8,SF.STOREPRIMARY[],2,FALSE)) -> App. For Employer SF/001 | C8: =IF(A8="","",VLOOKUP(A8,'STOCK CONTROL SHEET'!Details,3,FALSE)) -> PCS | D8: =SF.STOREPRIMARY[Reorder Levels] -> 15000 | E8: =SF.STOREPRIMARY[Physical Stock Bal.] -> 6000 | G8: =SFMaterialNo -> 100139 | H8: =IF(Table2[[#This Row],[Quantity]]>Table2[[#This Row],[Reorder Levels]],Table2[Item Description],"") | I8: =IF(Table2[[#This Row],[Quantity]]<=Table2[[#This Row],[Reorder Levels]],Table2[Item Description],"") -> App. For Employer SF/001
A9: =SFMaterialNo -> 100218 | B9: =IF(A9="","",VLOOKUP(A9,SF.STOREPRIMARY[],2,FALSE)) -> Ben. App. Forms SF/001 | C9: =IF(A9="","",VLOOKUP(A9,'STOCK CONTROL SHEET'!Details,3,FALSE)) -> PCS | D9: =SF.STOREPRIMARY[Reorder Levels] -> 7500 | E9: =SF.STOREPRIMARY[Physical Stock Bal.] -> 5150 | G9: =SFMaterialNo -> 100218 | H9: =IF(Table2[[#This Row],[Quantity]]>Table2[[#This Row],[Reorder Levels]],Table2[Item Description],"") | I9: =IF(Table2[[#This Row],[Quantity]]<=Table2[[#This Row],[Reorder Levels]],Table2[Item Description],"") -> Ben. App. Forms SF/001
A10: =SFMaterialNo -> 100220 | B10: =IF(A10="","",VLOOKUP(A10,SF.STOREPRIMARY[],2,FALSE)) -> Payment of Benefit Forms/004 | C10: =IF(A10="","",VLOOKUP(A10,'STOCK CONTROL SHEET'!Details,3,FALSE)) -> PCS | D10: =SF.STOREPRIMARY[Reorder Levels] -> 7500 | E10: =SF.STOREPRIMARY[Physical Stock Bal.] | G10: =SFMaterialNo -> 100220 | H10: =IF(Table2[[#This Row],[Quantity]]>Table2[[#This Row],[Reorder Levels]],Table2[Item Description],"") -> Payment of Benefit Forms/004 | I10: =IF(Table2[[#This Row],[Quantity]]<=Table2[[#This Row],[Reorder Levels]],Table2[Item Description],"")
A11: =SFMaterialNo -> 100210 | B11: =IF(A11="","",VLOOKUP(A11,SF.STOREPRIMARY[],2,FALSE)) -> Claim Confirmation SF/D/005 | C11: =IF(A11="","",VLOOKUP(A11,'STOCK CONTROL SHEET'!Details,3,FALSE)) -> PCS | D11: =SF.STOREPRIMARY[Reorder Levels] -> 7500 | E11: =SF.STOREPRIMARY[Physical Stock Bal.] -> 0 | G11: =SFMaterialNo -> 100210 | H11: =IF(Table2[[#This Row],[Quantity]]>Table2[[#This Row],[Reorder Levels]],Table2[Item Description],"") | I11: =IF(Table2[[#This Row],[Quantity]]<=Table2[[#This Row],[Reorder Levels]],Table2[Item Description],"") -> Claim Confirmation SF/D/005
A12: =SFMaterialNo -> 100162 | B12: =IF(A12="","",VLOOKUP(A12,SF.STOREPRIMARY[],2,FALSE)) -> Confidential Folders Pink | C12: =IF(A12="","",VLOOKUP(A12,'STOCK CONTROL SHEET'!Details,3,FALSE)) -> PCS | D12: =SF.STOREPRIMARY[Reorder Levels] -> 250 | E12: =SF.STOREPRIMARY[Physical Stock Bal.] -> 5 | G12: =SFMaterialNo -> 100162 | H12: =IF(Table2[[#This Row],[Quantity]]>Table2[[#This Row],[Reorder Levels]],Table2[Item Description],"") | I12: =IF(Table2[[#This Row],[Quantity]]<=Table2[[#This Row],[Reorder Levels]],Table2[Item Description],"") -> Confidential Folders Pink
A13: =SFMaterialNo -> 100144 | B13: =IF(A13="","",VLOOKUP(A13,SF.STOREPRIMARY[],2,FALSE)) -> Dummy B Certificate | C13: =IF(A13="","",VLOOKUP(A13,'STOCK CONTROL SHEET'!Details,3,FALSE)) -> PCS | D13: =SF.STOREPRIMARY[Reorder Levels] -> 100 | E13: =SF.STOREPRIMARY[Physical Stock Bal.] -> 201 | G13: =SFMaterialNo -> 100144 | H13: =IF(Table2[[#This Row],[Quantity]]>Table2[[#This Row],[Reorder Levels]],Table2[Item Description],"") -> Dummy B Certificate | I13: =IF(Table2[[#This Row],[Quantity]]<=Table2[[#This Row],[Reorder Levels]],Table2[Item Description],"")
A14: =SFMaterialNo -> 100125 | B14: =IF(A14="","",VLOOKUP(A14,SF.STOREPRIMARY[],2,FALSE)) -> Empty Cartons | C14: =IF(A14="","",VLOOKUP(A14,'STOCK CONTROL SHEET'!Details,3,FALSE)) -> NO | D14: =SF.STOREPRIMARY[Reorder Levels] -> 100 | E14: =SF.STOREPRIMARY[Physical Stock Bal.] -> 367 | G14: =SFMaterialNo -> 100125 | H14: =IF(Table2[[#This Row],[Quantity]]>Table2[[#This Row],[Reorder Levels]],Table2[Item Description],"") -> Empty Cartons | I14: =IF(Table2[[#This Row],[Quantity]]<=Table2[[#This Row],[Reorder Levels]],Table2[Item Description],"")
A15: =SFMaterialNo -> 100123 | B15: =IF(A15="","",VLOOKUP(A15,SF.STOREPRIMARY[],2,FALSE)) -> Envelopes A4 | C15: =IF(A15="","",VLOOKUP(A15,'STOCK CONTROL SHEET'!Details,3,FALSE)) -> PCS | D15: =SF.STOREPRIMARY[Reorder Levels] -> 9000 | E15: =SF.STOREPRIMARY[Physical Stock Bal.] -> 12851 | G15: =SFMaterialNo -> 100123 | H15: =IF(Table2[[#This Row],[Quantity]]>Table2[[#This Row],[Reorder Levels]],Table2[Item Description],"") -> Envelopes A4 | I15: =IF(Table2[[#This Row],[Quantity]]<=Table2[[#This Row],[Reorder Levels]],Table2[Item Description],"")
A16: =SFMaterialNo -> 100228 | B16: =IF(A16="","",VLOOKUP(A16,SF.STOREPRIMARY[],2,FALSE)) -> A3 Security Envelopes | C16: =IF(A16="","",VLOOKUP(A16,'STOCK CONTROL SHEET'!Details,3,FALSE)) -> PCS | D16: =SF.STOREPRIMARY[Reorder Levels] -> 600 | E16: =SF.STOREPRIMARY[Physical Stock Bal.] -> 0 | G16: =SFMaterialNo -> 100228 | H16: =IF(Table2[[#This Row],[Quantity]]>Table2[[#This Row],[Reorder Levels]],Table2[Item Description],"") | I16: =IF(Table2[[#This Row],[Quantity]]<=Table2[[#This Row],[Reorder Levels]],Table2[Item Description],"") -> A3 Security Envelopes
... A38: =SFMaterialNo -> 100127 | B38: =IF(A38="","",VLOOKUP(A38,SF.STOREPRIMARY[],2,FALSE)) -> Withdrawal Ben. Folders | C38: =IF(A38="","",VLOOKUP(A38,'STOCK CONTROL SHEET'!Details,3,FALSE)) -> PCS | D38: =SF.STOREPRIMARY[Reorder Levels] -> 5000 | E38: =SF.STOREPRIMARY[Physical Stock Bal.] -> 750 | G38: =SFMaterialNo -> 100127 | H38: =IF(Table2[[#This Row],[Quantity]]>Table2[[#This Row],[Reorder Levels]],Table2[Item Description],"") | I38: =IF(Table2[[#This Row],[Quantity]]<=Table2[[#This Row],[Reorder Levels]],Table2[Item Description],"") -> Withdrawal Ben. Folders
A39: =COMPMaterialNo -> 100172 | B39: =IF(A39="","",VLOOKUP(A39,COMP.STOREPRIMARY,2,FALSE)) -> 1 Part Statement Paper | C39: =IF(A39="","",VLOOKUP(A39,'STOCK CONTROL SHEET'!Details,3,FALSE)) -> PCS | D39: =COMP.STOREReorderLevels -> 150000 | E39: =COMP.STOREPhysicalBal. -> 235000 | F39: COMPUTER STORE | G39: =COMPMaterialNo -> 100172 | H39: =IF(Table2[[#This Row],[Quantity]]>Table2[[#This Row],[Reorder Levels]],Table2[Item Description],"") -> 1 Part Statement Paper | I39: =IF(Table2[[#This Row],[Quantity]]<=Table2[[#This Row],[Reorder Levels]],Table2[Item Description],"")
A40: =COMPMaterialNo -> 41 | B40: =IF(A40="","",VLOOKUP(A40,COMP.STOREPRIMARY,2,FALSE)) -> Tonner Kit TK-8525 (Magenta) | C40: =IF(A40="","",VLOOKUP(A40,'STOCK CONTROL SHEET'!Details,3,FALSE)) -> NO | D40: =COMP.STOREReorderLevels -> 0 | E40: =COMP.STOREPhysicalBal. -> 0 | G40: =COMPMaterialNo -> 41 | H40: =IF(Table2[[#This Row],[Quantity]]>Table2[[#This Row],[Reorder Levels]],Table2[Item Description],"") | I40: =IF(Table2[[#This Row],[Quantity]]<=Table2[[#This Row],[Reorder Levels]],Table2[Item Description],"") -> Tonner Kit TK-8525 (Magenta)
A41: =COMPMaterialNo -> 0 | B41: =IF(A41="","",VLOOKUP(A41,COMP.STOREPRIMARY,2,FALSE)) -> #N/A | C41: =IF(A41="","",VLOOKUP(A41,'STOCK CONTROL SHEET'!Details,3,FALSE)) -> #N/A | D41: =COMP.STOREReorderLevels -> 0 | E41: =COMP.STOREPhysicalBal. -> 3 | G41: =COMPMaterialNo -> 0 | H41: =IF(Table2[[#This Row],[Quantity]]>Table2[[#This Row],[Reorder Levels]],Table2[Item Description],"") -> #N/A | I41: =IF(Table2[[#This Row],[Quantity]]<=Table2[[#This Row],[Reorder Levels]],Table2[Item Description],"")
A42: =COMPMaterialNo -> 0 | B42: =IF(A42="","",VLOOKUP(A42,COMP.STOREPRIMARY,2,FALSE)) -> #N/A | C42: =IF(A42="","",VLOOKUP(A42,'STOCK CONTROL SHEET'!Details,3,FALSE)) -> #N/A | D42: =COMP.STOREReorderLevels -> 0 | E42: =COMP.STOREPhysicalBal. -> 1 | G42: =COMPMaterialNo -> 0 | H42: =IF(Table2[[#This Row],[Quantity]]>Table2[[#This Row],[Reorder Levels]],Table2[Item Description],"") -> #N/A | I42: =IF(Table2[[#This Row],[Quantity]]<=Table2[[#This Row],[Reorder Levels]],Table2[Item Description],"")
A43: =COMPMaterialNo -> 0 | B43: =IF(A43="","",VLOOKUP(A43,COMP.STOREPRIMARY,2,FALSE)) -> #N/A | C43: =IF(A43="","",VLOOKUP(A43,'STOCK CONTROL SHEET'!Details,3,FALSE)) -> #N/A | D43: =COMP.STOREReorderLevels -> 0 | E43: =COMP.STOREPhysicalBal. -> 5 | G43: =COMPMaterialNo -> 0 | H43: =IF(Table2[[#This Row],[Quantity]]>Table2[[#This Row],[Reorder Levels]],Table2[Item Description],"") -> #N/A | I43: =IF(Table2[[#This Row],[Quantity]]<=Table2[[#This Row],[Reorder Levels]],Table2[Item Description],"")
A44: =COMPMaterialNo -> 0 | B44: =IF(A44="","",VLOOKUP(A44,COMP.STOREPRIMARY,2,FALSE)) -> #N/A | C44: =IF(A44="","",VLOOKUP(A44,'STOCK CONTROL SHEET'!Details,3,FALSE)) -> #N/A | D44: =COMP.STOREReorderLevels -> 0 | E44: =COMP.STOREPhysicalBal. -> 7 | G44: =COMPMaterialNo -> 0 | H44: =IF(Table2[[#This Row],[Quantity]]>Table2[[#This Row],[Reorder Levels]],Table2[Item Description],"") -> #N/A | I44: =IF(Table2[[#This Row],[Quantity]]<=Table2[[#This Row],[Reorder Levels]],Table2[Item Description],"")
A45: =COMPMaterialNo -> 0 | B45: =IF(A45="","",VLOOKUP(A45,COMP.STOREPRIMARY,2,FALSE)) -> #N/A | C45: =IF(A45="","",VLOOKUP(A45,'STOCK CONTROL SHEET'!Details,3,FALSE)) -> #N/A | D45: =COMP.STOREReorderLevels -> 0 | E45: =COMP.STOREPhysicalBal. -> 6 | G45: =COMPMaterialNo -> 0 | H45: =IF(Table2[[#This Row],[Quantity]]>Table2[[#This Row],[Reorder Levels]],Table2[Item Description],"") -> #N/A | I45: =IF(Table2[[#This Row],[Quantity]]<=Table2[[#This Row],[Reorder Levels]],Table2[Item Description],"")
A46: =COMPMaterialNo -> 100229 | B46: =IF(A46="","",VLOOKUP(A46,COMP.STOREPRIMARY,2,FALSE)) -> 2 PP NCR Carbonated | C46: =IF(A46="","",VLOOKUP(A46,'STOCK CONTROL SHEET'!Details,3,FALSE)) -> PCS | D46: =COMP.STOREReorderLevels -> 150000 | E46: =COMP.STOREPhysicalBal. -> 230000 | G46: =COMPMaterialNo -> 100229 | H46: =IF(Table2[[#This Row],[Quantity]]>Table2[[#This Row],[Reorder Levels]],Table2[Item Description],"") -> 2 PP NCR Carbonated | I46: =IF(Table2[[#This Row],[Quantity]]<=Table2[[#This Row],[Reorder Levels]],Table2[Item Description],"")
A47: =COMPMaterialNo -> 200033 | B47: =IF(A47="","",VLOOKUP(A47,COMP.STOREPRIMARY,2,FALSE)) -> Epson Ribbon 2180 | C47: =IF(A47="","",VLOOKUP(A47,'STOCK CONTROL SHEET'!Details,3,FALSE)) -> PCS | D47: =COMP.STOREReorderLevels -> 0 | E47: =COMP.STOREPhysicalBal. -> 53 | G47: =COMPMaterialNo -> 200033 | H47: =IF(Table2[[#This Row],[Quantity]]>Table2[[#This Row],[Reorder Levels]],Table2[Item Description],"") -> Epson Ribbon 2180 | I47: =IF(Table2[[#This Row],[Quantity]]<=Table2[[#This Row],[Reorder Levels]],Table2[Item Description],"")
A48: =COMPMaterialNo -> 37 | B48: =IF(A48="","",VLOOKUP(A48,COMP.STOREPRIMARY,2,FALSE)) -> Epson EB Projector/amp | C48: =IF(A48="","",VLOOKUP(A48,'STOCK CONTROL SHEET'!Details,3,FALSE)) -> NO | D48: =COMP.STOREReorderLevels -> 0 | E48: =COMP.STOREPhysicalBal. -> 0 | G48: =COMPMaterialNo -> 37 | H48: =IF(Table2[[#This Row],[Quantity]]>Table2[[#This Row],[Reorder Levels]],Table2[Item Description],"") | I48: =IF(Table2[[#This Row],[Quantity]]<=Table2[[#This Row],[Reorder Levels]],Table2[Item Description],"") -> Epson EB Projector/amp
A49: =COMPMaterialNo -> 200033 | B49: =IF(A49="","",VLOOKUP(A49,COMP.STOREPRIMARY,2,FALSE)) -> Epson Ribbon 2180 | C49: =IF(A49="","",VLOOKUP(A49,'STOCK CONTROL SHEET'!Details,3,FALSE)) -> PCS | D49: =COMP.STOREReorderLevels -> 0 | E49: =COMP.STOREPhysicalBal. -> 11 | G49: =COMPMaterialNo -> 200033 | H49: =IF(Table2[[#This Row],[Quantity]]>Table2[[#This Row],[Reorder Levels]],Table2[Item Description],"") -> Epson Ribbon 2180 | I49: =IF(Table2[[#This Row],[Quantity]]<=Table2[[#This Row],[Reorder Levels]],Table2[Item Description],"")
A50: =COMPMaterialNo -> 0 | B50: =IF(A50="","",VLOOKUP(A50,COMP.STOREPRIMARY,2,FALSE)) -> #N/A | C50: =IF(A50="","",VLOOKUP(A50,'STOCK CONTROL SHEET'!Details,3,FALSE)) -> #N/A | D50: =COMP.STOREReorderLevels -> 0 | E50: =COMP.STOREPhysicalBal. -> 9 | G50: =COMPMaterialNo -> 0 | H50: =IF(Table2[[#This Row],[Quantity]]>Table2[[#This Row],[Reorder Levels]],Table2[Item Description],"") -> #N/A | I50: =IF(Table2[[#This Row],[Quantity]]<=Table2[[#This Row],[Reorder Levels]],Table2[Item Description],"")
A51: =COMPMaterialNo -> 0 | B51: =IF(A51="","",VLOOKUP(A51,COMP.STOREPRIMARY,2,FALSE)) -> #N/A | C51: =IF(A51="","",VLOOKUP(A51,'STOCK CONTROL SHEET'!Details,3,FALSE)) -> #N/A | D51: =COMP.STOREReorderLevels -> 0 | E51: =COMP.STOREPhysicalBal. -> 6 | G51: =COMPMaterialNo -> 0 | H51: =IF(Table2[[#This Row],[Quantity]]>Table2[[#This Row],[Reorder Levels]],Table2[Item Description],"") -> #N/A | I51: =IF(Table2[[#This Row],[Quantity]]<=Table2[[#This Row],[Reorder Levels]],Table2[Item Description],"")
... A124: =COMPMaterialNo -> 200017 | B124: =IF(A124="","",VLOOKUP(A124,COMP.STOREPRIMARY,2,FALSE)) -> Lex Mark C920 Ribbon Magenta | C124: =IF(A124="","",VLOOKUP(A124,'STOCK CONTROL SHEET'!Details,3,FALSE)) -> NO | D124: =COMP.STOREReorderLevels -> 1 | E124: =COMP.STOREPhysicalBal. -> 7 | G124: =COMPMaterialNo -> 200017 | H124: =IF(Table2[[#This Row],[Quantity]]>Table2[[#This Row],[Reorder Levels]],Table2[Item Description],"") -> Lex Mark C920 Ribbon Magenta | I124: =IF(Table2[[#This Row],[Quantity]]<=Table2[[#This Row],[Reorder Levels]],Table2[Item Description],"")
A125: =MAINTMaterialNo -> 282022 | B125: =IF(A125="","",VLOOKUP(A125,MAINT.STOREPRIMARY,2,FALSE)) -> Air Freshener | C125: =IF(A125="","",VLOOKUP(A125,'STOCK CONTROL SHEET'!Details,3,FALSE)) -> NO | D125: =MAINT.STOREReorderLevels -> 0 | E125: =MAINT.STOREPhysicalStockBal. -> 34 | F125: MAINTENANCE STORE | G125: =MAINTMaterialNo -> 282022 | H125: =IF(Table2[[#This Row],[Quantity]]>Table2[[#This Row],[Reorder Levels]],Table2[Item Description],"") -> Air Freshener | I125: =IF(Table2[[#This Row],[Quantity]]<=Table2[[#This Row],[Reorder Levels]],Table2[Item Description],"")
A126: =MAINTMaterialNo -> 282018 | B126: =IF(A126="","",VLOOKUP(A126,MAINT.STOREPRIMARY,2,FALSE)) -> Bar Soaps | C126: =IF(A126="","",VLOOKUP(A126,'STOCK CONTROL SHEET'!Details,3,FALSE)) -> PCS | D126: =MAINT.STOREReorderLevels -> 0 | E126: =MAINT.STOREPhysicalStockBal. -> 336 | G126: =MAINTMaterialNo -> 282018 | H126: =IF(Table2[[#This Row],[Quantity]]>Table2[[#This Row],[Reorder Levels]],Table2[Item Description],"") -> Bar Soaps | I126: =IF(Table2[[#This Row],[Quantity]]<=Table2[[#This Row],[Reorder Levels]],Table2[Item Description],"")
A127: =MAINTMaterialNo -> 252014 | B127: =IF(A127="","",VLOOKUP(A127,MAINT.STOREPRIMARY,2,FALSE)) -> 4-Way Extension Socket | C127: =IF(A127="","",VLOOKUP(A127,'STOCK CONTROL SHEET'!Details,3,FALSE)) -> NO | D127: =MAINT.STOREReorderLevels -> 6 | E127: =MAINT.STOREPhysicalStockBal. -> 23 | G127: =MAINTMaterialNo -> 252014 | H127: =IF(Table2[[#This Row],[Quantity]]>Table2[[#This Row],[Reorder Levels]],Table2[Item Description],"") -> 4-Way Extension Socket | I127: =IF(Table2[[#This Row],[Quantity]]<=Table2[[#This Row],[Reorder Levels]],Table2[Item Description],"")
A128: =MAINTMaterialNo -> 252015 | B128: =IF(A128="","",VLOOKUP(A128,MAINT.STOREPRIMARY,2,FALSE)) -> Single Socket | C128: =IF(A128="","",VLOOKUP(A128,'STOCK CONTROL SHEET'!Details,3,FALSE)) -> NO | D128: =MAINT.STOREReorderLevels -> 0 | E128: =MAINT.STOREPhysicalStockBal. -> 24 | G128: =MAINTMaterialNo -> 252015 | H128: =IF(Table2[[#This Row],[Quantity]]>Table2[[#This Row],[Reorder Levels]],Table2[Item Description],"") -> Single Socket | I128: =IF(Table2[[#This Row],[Quantity]]<=Table2[[#This Row],[Reorder Levels]],Table2[Item Description],"")
A129: =MAINTMaterialNo -> 252018 | B129: =IF(A129="","",VLOOKUP(A129,MAINT.STOREPRIMARY,2,FALSE)) -> 13 Amps Top Plug | C129: =IF(A129="","",VLOOKUP(A129,'STOCK CONTROL SHEET'!Details,3,FALSE)) -> NO | D129: =MAINT.STOREReorderLevels -> 4 | E129: =MAINT.STOREPhysicalStockBal. -> 25 | G129: =MAINTMaterialNo -> 252018 | H129: =IF(Table2[[#This Row],[Quantity]]>Table2[[#This Row],[Reorder Levels]],Table2[Item Description],"") -> 13 Amps Top Plug | I129: =IF(Table2[[#This Row],[Quantity]]<=Table2[[#This Row],[Reorder Levels]],Table2[Item Description],"")
A130: =MAINTMaterialNo -> 100 | B130: =IF(A130="","",VLOOKUP(A130,MAINT.STOREPRIMARY,2,FALSE)) -> 40 Amp Tap of Unit | C130: =IF(A130="","",VLOOKUP(A130,'STOCK CONTROL SHEET'!Details,3,FALSE)) -> NO | D130: =MAINT.STOREReorderLevels -> 0 | E130: =MAINT.STOREPhysicalStockBal. -> 0 | G130: =MAINTMaterialNo -> 100 | H130: =IF(Table2[[#This Row],[Quantity]]>Table2[[#This Row],[Reorder Levels]],Table2[Item Description],"") | I130: =IF(Table2[[#This Row],[Quantity]]<=Table2[[#This Row],[Reorder Levels]],Table2[Item Description],"") -> 40 Amp Tap of Unit
A131: =MAINTMaterialNo -> 101 | B131: =IF(A131="","",VLOOKUP(A131,MAINT.STOREPRIMARY,2,FALSE)) -> Blower | C131: =IF(A131="","",VLOOKUP(A131,'STOCK CONTROL SHEET'!Details,3,FALSE)) -> NO | D131: =MAINT.STOREReorderLevels -> 0 | E131: =MAINT.STOREPhysicalStockBal. -> 1 | G131: =MAINTMaterialNo -> 101 | H131: =IF(Table2[[#This Row],[Quantity]]>Table2[[#This Row],[Reorder Levels]],Table2[Item Description],"") -> Blower | I131: =IF(Table2[[#This Row],[Quantity]]<=Table2[[#This Row],[Reorder Levels]],Table2[Item Description],"")
A132: =MAINTMaterialNo -> 252040 | B132: =IF(A132="","",VLOOKUP(A132,MAINT.STOREPRIMARY,2,FALSE)) -> Chokes 4/6/8 | C132: =IF(A132="","",VLOOKUP(A132,'STOCK CONTROL SHEET'!Details,3,FALSE)) -> NO | D132: =MAINT.STOREReorderLevels -> 0 | E132: =MAINT.STOREPhysicalStockBal. -> 50 | G132: =MAINTMaterialNo -> 252040 | H132: =IF(Table2[[#This Row],[Quantity]]>Table2[[#This Row],[Reorder Levels]],Table2[Item Description],"") -> Chokes 4/6/8 | I132: =IF(Table2[[#This Row],[Quantity]]<=Table2[[#This Row],[Reorder Levels]],Table2[Item Description],"")
A133: =MAINTMaterialNo -> 272002 | B133: =IF(A133="","",VLOOKUP(A133,MAINT.STOREPRIMARY,2,FALSE)) -> Disposable Gloves | C133: =IF(A133="","",VLOOKUP(A133,'STOCK CONTROL SHEET'!Details,3,FALSE)) -> PAIRS | D133: =MAINT.STOREReorderLevels -> 0 | E133: =MAINT.STOREPhysicalStockBal. -> 100 | G133: =MAINTMaterialNo -> 272002 | H133: =IF(Table2[[#This Row],[Quantity]]>Table2[[#This Row],[Reorder Levels]],Table2[Item Description],"") -> Disposable Gloves | I133: =IF(Table2[[#This Row],[Quantity]]<=Table2[[#This Row],[Reorder Levels]],Table2[Item Description],"")
A134: =MAINTMaterialNo -> 252028 | B134: =IF(A134="","",VLOOKUP(A134,MAINT.STOREPRIMARY,2,FALSE)) -> Door Closer | C134: =IF(A134="","",VLOOKUP(A134,'STOCK CONTROL SHEET'!Details,3,FALSE)) -> NO | D134: =MAINT.STOREReorderLevels -> 0 | E134: =MAINT.STOREPhysicalStockBal. -> 0 | G134: =MAINTMaterialNo -> 252028 | H134: =IF(Table2[[#This Row],[Quantity]]>Table2[[#This Row],[Reorder Levels]],Table2[Item Description],"") | I134: =IF(Table2[[#This Row],[Quantity]]<=Table2[[#This Row],[Reorder Levels]],Table2[Item Description],"") -> Door Closer
A135: =MAINTMaterialNo -> 105 | B135: =IF(A135="","",VLOOKUP(A135,MAINT.STOREPRIMARY,2,FALSE)) -> Data Cabinet | C135: =IF(A135="","",VLOOKUP(A135,'STOCK CONTROL SHEET'!Details,3,FALSE)) -> NO | D135: =MAINT.STOREReorderLevels -> 0 | E135: =MAINT.STOREPhysicalStockBal. | G135: =MAINTMaterialNo -> 105 | H135: =IF(Table2[[#This Row],[Quantity]]>Table2[[#This Row],[Reorder Levels]],Table2[Item Description],"") -> Data Cabinet | I135: =IF(Table2[[#This Row],[Quantity]]<=Table2[[#This Row],[Reorder Levels]],Table2[Item Description],"")
A136: =MAINTMaterialNo -> 282030 | B136: =IF(A136="","",VLOOKUP(A136,MAINT.STOREPRIMARY,2,FALSE)) -> Duster Washing Pads | C136: =IF(A136="","",VLOOKUP(A136,'STOCK CONTROL SHEET'!Details,3,FALSE)) -> NO | D136: =MAINT.STOREReorderLevels -> 0 | E136: =MAINT.STOREPhysicalStockBal. -> 0 | G136: =MAINTMaterialNo -> 282030 | H136: =IF(Table2[[#This Row],[Quantity]]>Table2[[#This Row],[Reorder Levels]],Table2[Item Description],"") | I136: =IF(Table2[[#This Row],[Quantity]]<=Table2[[#This Row],[Reorder Levels]],Table2[Item Description],"") -> Duster Washing Pads
A137: =MAINTMaterialNo -> 252026 | B137: =IF(A137="","",VLOOKUP(A137,MAINT.STOREPRIMARY,2,FALSE)) -> Deadlock Double Cylinder | C137: =IF(A137="","",VLOOKUP(A137,'STOCK CONTROL SHEET'!Details,3,FALSE)) -> NO | D137: =MAINT.STOREReorderLevels -> 10 | E137: =MAINT.STOREPhysicalStockBal. -> 0 | G137: =MAINTMaterialNo -> 252026 | H137: =IF(Table2[[#This Row],[Quantity]]>Table2[[#This Row],[Reorder Levels]],Table2[Item Description],"") | I137: =IF(Table2[[#This Row],[Quantity]]<=Table2[[#This Row],[Reorder Levels]],Table2[Item Description],"") -> Deadlock Double Cylinder
... A172: =MAINTMaterialNo -> 252017 | B172: =IF(A172="","",VLOOKUP(A172,MAINT.STOREPRIMARY,2,FALSE)) -> Toilet Seat Covers | C172: =IF(A172="","",VLOOKUP(A172,'STOCK CONTROL SHEET'!Details,3,FALSE)) -> NO | D172: =MAINT.STOREReorderLevels -> 0 | E172: =MAINT.STOREPhysicalStockBal. -> 19 | G172: =MAINTMaterialNo -> 252017 | H172: =IF(Table2[[#This Row],[Quantity]]>Table2[[#This Row],[Reorder Levels]],Table2[Item Description],"") -> Toilet Seat Covers | I172: =IF(Table2[[#This Row],[Quantity]]<=Table2[[#This Row],[Reorder Levels]],Table2[Item Description],"")

Sheet STORE PERFORMANCE
A1: VALUE OF DEFICIENCIES & SURPLUS | G1: RESPECTIVE DAILY STORE PERFOMANCE
A2: SF STORE | G2: Store | H2: Value of Deficiency | I2: Value of Surplus | J2: Row Labels | K2: Sum of Value of Deficiency | L2: Sum of Value of Surplus
A3: Material No | B3: Item Description | C3: Unit of Issue | D3: Quantity Deficit | E3: Quantity Surplus | G3: SF | H3: =SUM(Table8[Quantity Deficit]) -> #VALUE! | I3: =SUM(Table8[Quantity Surplus]) -> #VALUE! | J3: Grand Total | K3: #DIV/0! | L3: #DIV/0!
A4: =SFMaterialNo -> 282014 | B4: =IF(A4="","",VLOOKUP(A4,'STOCK CONTROL SHEET'!Details,2,FALSE)) -> Tissue Papers | C4: =IF(A4="","",VLOOKUP(A4,'STOCK CONTROL SHEET'!Details,3,FALSE)) -> ROLL | D4: =INDEX(SF.STOREPRIMARY[],MATCH('STORE PERFORMANCE'!A4,SFMaterialNo,0),9) | E4: =INDEX(SF.STOREPRIMARY[],MATCH('STORE PERFORMANCE'!A4,SF.STOREPRIMARY[Material No],0),10) | G4: Computer | H4: =SUM(Table9[Quantity Deficit]) -> 36 | I4: =SUM(Table9[Quantity Surplus]) -> 342102
A5: =SFMaterialNo -> 100126 | B5: =IF(A5="","",VLOOKUP(A5,'STOCK CONTROL SHEET'!Details,2,FALSE)) -> Administration Folders | C5: =IF(A5="","",VLOOKUP(A5,'STOCK CONTROL SHEET'!Details,3,FALSE)) -> PCS | D5: =INDEX(SF.STOREPRIMARY[],MATCH('STORE PERFORMANCE'!A5,SFMaterialNo,0),9) -> 375 | E5: =INDEX(SF.STOREPRIMARY[],MATCH('STORE PERFORMANCE'!A5,SF.STOREPRIMARY[Material No],0),10) | G5: Maintenance | H5: =SUM(Table10[Quantity Deficit]) -> #VALUE! | I5: =SUM(Table10[Quantity Surplus]) -> #VALUE!
A6: =SFMaterialNo -> 100128 | B6: =IF(A6="","",VLOOKUP(A6,'STOCK CONTROL SHEET'!Details,2,FALSE)) -> Age Benefit Folders | C6: =IF(A6="","",VLOOKUP(A6,'STOCK CONTROL SHEET'!Details,3,FALSE)) -> PCS | D6: =INDEX(SF.STOREPRIMARY[],MATCH('STORE PERFORMANCE'!A6,SFMaterialNo,0),9) | E6: =INDEX(SF.STOREPRIMARY[],MATCH('STORE PERFORMANCE'!A6,SF.STOREPRIMARY[Material No],0),10) -> 76
A7: =SFMaterialNo -> 100216 | B7: =IF(A7="","",VLOOKUP(A7,'STOCK CONTROL SHEET'!Details,2,FALSE)) -> App. For Personal Exemption Forms | C7: =IF(A7="","",VLOOKUP(A7,'STOCK CONTROL SHEET'!Details,3,FALSE)) -> PCS | D7: =INDEX(SF.STOREPRIMARY[],MATCH('STORE PERFORMANCE'!A7,SFMaterialNo,0),9) | E7: =INDEX(SF.STOREPRIMARY[],MATCH('STORE PERFORMANCE'!A7,SF.STOREPRIMARY[Material No],0),10) | G7: Total | H7: =SUM(Table5[Value of Deficiency]) -> #VALUE! | I7: =SUM(Table5[Value of Surplus]) -> #VALUE!
A8: =SFMaterialNo -> 100139 | B8: =IF(A8="","",VLOOKUP(A8,'STOCK CONTROL SHEET'!Details,2,FALSE)) -> App. For Employer SF/001 | C8: =IF(A8="","",VLOOKUP(A8,'STOCK CONTROL SHEET'!Details,3,FALSE)) -> PCS | D8: =INDEX(SF.STOREPRIMARY[],MATCH('STORE PERFORMANCE'!A8,SFMaterialNo,0),9) -> 2750 | E8: =INDEX(SF.STOREPRIMARY[],MATCH('STORE PERFORMANCE'!A8,SF.STOREPRIMARY[Material No],0),10)
A9: =SFMaterialNo -> 100218 | B9: =IF(A9="","",VLOOKUP(A9,'STOCK CONTROL SHEET'!Details,2,FALSE)) -> Ben. App. Forms SF/001 | C9: =IF(A9="","",VLOOKUP(A9,'STOCK CONTROL SHEET'!Details,3,FALSE)) -> PCS | D9: =INDEX(SF.STOREPRIMARY[],MATCH('STORE PERFORMANCE'!A9,SFMaterialNo,0),9) -> 3800 | E9: =INDEX(SF.STOREPRIMARY[],MATCH('STORE PERFORMANCE'!A9,SF.STOREPRIMARY[Material No],0),10)
A10: =SFMaterialNo -> 100220 | B10: =IF(A10="","",VLOOKUP(A10,'STOCK CONTROL SHEET'!Details,2,FALSE)) -> Payment of Benefit Forms/004 | C10: =IF(A10="","",VLOOKUP(A10,'STOCK CONTROL SHEET'!Details,3,FALSE)) -> PCS | D10: =INDEX(SF.STOREPRIMARY[],MATCH('STORE PERFORMANCE'!A10,SFMaterialNo,0),9) -> #VALUE! | E10: =INDEX(SF.STOREPRIMARY[],MATCH('STORE PERFORMANCE'!A10,SF.STOREPRIMARY[Material No],0),10) -> #VALUE!
A11: =SFMaterialNo -> 100210 | B11: =IF(A11="","",VLOOKUP(A11,'STOCK CONTROL SHEET'!Details,2,FALSE)) -> Claim Confirmation SF/D/005 | C11: =IF(A11="","",VLOOKUP(A11,'STOCK CONTROL SHEET'!Details,3,FALSE)) -> PCS | D11: =INDEX(SF.STOREPRIMARY[],MATCH('STORE PERFORMANCE'!A11,SFMaterialNo,0),9) | E11: =INDEX(SF.STOREPRIMARY[],MATCH('STORE PERFORMANCE'!A11,SF.STOREPRIMARY[Material No],0),10)
A12: =SFMaterialNo -> 100162 | B12: =IF(A12="","",VLOOKUP(A12,'STOCK CONTROL SHEET'!Details,2,FALSE)) -> Confidential Folders Pink | C12: =IF(A12="","",VLOOKUP(A12,'STOCK CONTROL SHEET'!Details,3,FALSE)) -> PCS | D12: =INDEX(SF.STOREPRIMARY[],MATCH('STORE PERFORMANCE'!A12,SFMaterialNo,0),9) -> 165 | E12: =INDEX(SF.STOREPRIMARY[],MATCH('STORE PERFORMANCE'!A12,SF.STOREPRIMARY[Material No],0),10)
A13: =SFMaterialNo -> 100144 | B13: =IF(A13="","",VLOOKUP(A13,'STOCK CONTROL SHEET'!Details,2,FALSE)) -> Dummy B Certificate | C13: =IF(A13="","",VLOOKUP(A13,'STOCK CONTROL SHEET'!Details,3,FALSE)) -> PCS | D13: =INDEX(SF.STOREPRIMARY[],MATCH('STORE PERFORMANCE'!A13,SFMaterialNo,0),9) | E13: =INDEX(SF.STOREPRIMARY[],MATCH('STORE PERFORMANCE'!A13,SF.STOREPRIMARY[Material No],0),10)
A14: =SFMaterialNo -> 100125 | B14: =IF(A14="","",VLOOKUP(A14,'STOCK CONTROL SHEET'!Details,2,FALSE)) -> Empty Cartons | C14: =IF(A14="","",VLOOKUP(A14,'STOCK CONTROL SHEET'!Details,3,FALSE)) -> NO | D14: =INDEX(SF.STOREPRIMARY[],MATCH('STORE PERFORMANCE'!A14,SFMaterialNo,0),9) -> 130 | E14: =INDEX(SF.STOREPRIMARY[],MATCH('STORE PERFORMANCE'!A14,SF.STOREPRIMARY[Material No],0),10)
A15: =SFMaterialNo -> 100123 | B15: =IF(A15="","",VLOOKUP(A15,'STOCK CONTROL SHEET'!Details,2,FALSE)) -> Envelopes A4 | C15: =IF(A15="","",VLOOKUP(A15,'STOCK CONTROL SHEET'!Details,3,FALSE)) -> PCS | D15: =INDEX(SF.STOREPRIMARY[],MATCH('STORE PERFORMANCE'!A15,SFMaterialNo,0),9) | E15: =INDEX(SF.STOREPRIMARY[],MATCH('STORE PERFORMANCE'!A15,SF.STOREPRIMARY[Material No],0),10) -> 3206
A16: =SFMaterialNo -> 100228 | B16: =IF(A16="","",VLOOKUP(A16,'STOCK CONTROL SHEET'!Details,2,FALSE)) -> A3 Security Envelopes | C16: =IF(A16="","",VLOOKUP(A16,'STOCK CONTROL SHEET'!Details,3,FALSE)) -> PCS | D16: =INDEX(SF.STOREPRIMARY[],MATCH('STORE PERFORMANCE'!A16,SFMaterialNo,0),9) -> 10 | E16: =INDEX(SF.STOREPRIMARY[],MATCH('STORE PERFORMANCE'!A16,SF.STOREPRIMARY[Material No],0),10)
A17: =SFMaterialNo -> 100124 | B17: =IF(A17="","",VLOOKUP(A17,'STOCK CONTROL SHEET'!Details,2,FALSE)) -> Envelopes A3 (16*12) White | C17: =IF(A17="","",VLOOKUP(A17,'STOCK CONTROL SHEET'!Details,3,FALSE)) -> PCS | D17: =INDEX(SF.STOREPRIMARY[],MATCH('STORE PERFORMANCE'!A17,SFMaterialNo,0),9) | E17: =INDEX(SF.STOREPRIMARY[],MATCH('STORE PERFORMANCE'!A17,SF.STOREPRIMARY[Material No],0),10) -> 25
A18: =SFMaterialNo -> 100122 | B18: =IF(A18="","",VLOOKUP(A18,'STOCK CONTROL SHEET'!Details,2,FALSE)) -> Envelopes A5 | C18: =IF(A18="","",VLOOKUP(A18,'STOCK CONTROL SHEET'!Details,3,FALSE)) -> PCS | D18: =INDEX(SF.STOREPRIMARY[],MATCH('STORE PERFORMANCE'!A18,SFMaterialNo,0),9) -> 3579 | E18: =INDEX(SF.STOREPRIMARY[],MATCH('STORE PERFORMANCE'!A18,SF.STOREPRIMARY[Material No],0),10)
A19: =SFMaterialNo -> 100130 | B19: =IF(A19="","",VLOOKUP(A19,'STOCK CONTROL SHEET'!Details,2,FALSE)) -> Emigration Benefit Folders | C19: =IF(A19="","",VLOOKUP(A19,'STOCK CONTROL SHEET'!Details,3,FALSE)) -> PCS | D19: =INDEX(SF.STOREPRIMARY[],MATCH('STORE PERFORMANCE'!A19,SFMaterialNo,0),9) | E19: =INDEX(SF.STOREPRIMARY[],MATCH('STORE PERFORMANCE'!A19,SF.STOREPRIMARY[Material No],0),10) -> 288
... A38: =SFMaterialNo -> 100127 | B38: =IF(A38="","",VLOOKUP(A38,'STOCK CONTROL SHEET'!Details,2,FALSE)) -> Withdrawal Ben. Folders | C38: =IF(A38="","",VLOOKUP(A38,'STOCK CONTROL SHEET'!Details,3,FALSE)) -> PCS | D38: =INDEX(SF.STOREPRIMARY[],MATCH('STORE PERFORMANCE'!A38,SFMaterialNo,0),9) -> 390 | E38: =INDEX(SF.STOREPRIMARY[],MATCH('STORE PERFORMANCE'!A38,SF.STOREPRIMARY[Material No],0),10)
A39: COMPUTER STORE
A40: Material No | B40: Item Description | C40: Unit of Issue | D40: Quantity Deficit | E40: Quantity Surplus
A41: 100172 | B41: =IF(A41="","",VLOOKUP(A41,'STOCK CONTROL SHEET'!Details,2,FALSE)) -> 1 Part Statement Paper | C41: =IF(A41="","",VLOOKUP(A41,'STOCK CONTROL SHEET'!Details,3,FALSE)) -> PCS | D41: =INDEX(COMP.STOREPRIMARY,MATCH('STORE PERFORMANCE'!A41,COMPMaterialNo,0),9) | E41: =INDEX(COMP.STOREPRIMARY,MATCH('STORE PERFORMANCE'!A41,COMPMaterialNo,0),10) -> 154000
A42: 100229 | B42: =IF(A42="","",VLOOKUP(A42,'STOCK CONTROL SHEET'!Details,2,FALSE)) -> 2 PP NCR Carbonated | C42: =IF(A42="","",VLOOKUP(A42,'STOCK CONTROL SHEET'!Details,3,FALSE)) -> PCS | D42: =INDEX(COMP.STOREPRIMARY,MATCH('STORE PERFORMANCE'!A42,COMPMaterialNo,0),9) | E42: =INDEX(COMP.STOREPRIMARY,MATCH('STORE PERFORMANCE'!A42,COMPMaterialNo,0),10) -> 178000
A43: 200033 | B43: =IF(A43="","",VLOOKUP(A43,'STOCK CONTROL SHEET'!Details,2,FALSE)) -> Epson Ribbon 2180 | C43: =IF(A43="","",VLOOKUP(A43,'STOCK CONTROL SHEET'!Details,3,FALSE)) -> PCS | D43: =INDEX(COMP.STOREPRIMARY,MATCH('STORE PERFORMANCE'!A43,COMPMaterialNo,0),9) | E43: =INDEX(COMP.STOREPRIMARY,MATCH('STORE PERFORMANCE'!A43,COMPMaterialNo,0),10) -> 2
A44: 37 | B44: =IF(A44="","",VLOOKUP(A44,'STOCK CONTROL SHEET'!Details,2,FALSE)) -> Epson EB Projector/amp | C44: =IF(A44="","",VLOOKUP(A44,'STOCK CONTROL SHEET'!Details,3,FALSE)) -> NO | D44: =INDEX(COMP.STOREPRIMARY,MATCH('STORE PERFORMANCE'!A44,COMPMaterialNo,0),9) | E44: =INDEX(COMP.STOREPRIMARY,MATCH('STORE PERFORMANCE'!A44,COMPMaterialNo,0),10)
A45: 200024 | B45: =IF(A45="","",VLOOKUP(A45,'STOCK CONTROL SHEET'!Details,2,FALSE)) -> Epson DFX 5000 Ribbon(8766) | C45: =IF(A45="","",VLOOKUP(A45,'STOCK CONTROL SHEET'!Details,3,FALSE)) -> PCS | D45: =INDEX(COMP.STOREPRIMARY,MATCH('STORE PERFORMANCE'!A45,COMPMaterialNo,0),9) | E45: =INDEX(COMP.STOREPRIMARY,MATCH('STORE PERFORMANCE'!A45,COMPMaterialNo,0),10) -> 7
A46: 200031 | B46: =IF(A46="","",VLOOKUP(A46,'STOCK CONTROL SHEET'!Details,2,FALSE)) -> Epson Ribbon LX 300 (8750) | C46: =IF(A46="","",VLOOKUP(A46,'STOCK CONTROL SHEET'!Details,3,FALSE)) -> NO | D46: =INDEX(COMP.STOREPRIMARY,MATCH('STORE PERFORMANCE'!A46,COMPMaterialNo,0),9) | E46: =INDEX(COMP.STOREPRIMARY,MATCH('STORE PERFORMANCE'!A46,COMPMaterialNo,0),10) -> 5
A47: 200030 | B47: =IF(A47="","",VLOOKUP(A47,'STOCK CONTROL SHEET'!Details,2,FALSE)) -> Epson DFX 9000 | C47: =IF(A47="","",VLOOKUP(A47,'STOCK CONTROL SHEET'!Details,3,FALSE)) -> NO | D47: =INDEX(COMP.STOREPRIMARY,MATCH('STORE PERFORMANCE'!A47,COMPMaterialNo,0),9) | E47: =INDEX(COMP.STOREPRIMARY,MATCH('STORE PERFORMANCE'!A47,COMPMaterialNo,0),10) -> 8
A48: 200067 | B48: =IF(A48="","",VLOOKUP(A48,'STOCK CONTROL SHEET'!Details,2,FALSE)) -> Epson Ribbon LQ 690 (Black) | C48: =IF(A48="","",VLOOKUP(A48,'STOCK CONTROL SHEET'!Details,3,FALSE)) -> NO | D48: =INDEX(COMP.STOREPRIMARY,MATCH('STORE PERFORMANCE'!A48,COMPMaterialNo,0),9) -> 23 | E48: =INDEX(COMP.STOREPRIMARY,MATCH('STORE PERFORMANCE'!A48,COMPMaterialNo,0),10)
A49: 200034 | B49: =IF(A49="","",VLOOKUP(A49,'STOCK CONTROL SHEET'!Details,2,FALSE)) -> Epson Ribbon LX 2090 FX | C49: =IF(A49="","",VLOOKUP(A49,'STOCK CONTROL SHEET'!Details,3,FALSE)) -> NO | D49: =INDEX(COMP.STOREPRIMARY,MATCH('STORE PERFORMANCE'!A49,COMPMaterialNo,0),9) | E49: =INDEX(COMP.STOREPRIMARY,MATCH('STORE PERFORMANCE'!A49,COMPMaterialNo,0),10)
A50: 200070 | B50: =IF(A50="","",VLOOKUP(A50,'STOCK CONTROL SHEET'!Details,2,FALSE)) -> HP Laserjet Tonner 237A Black | C50: =IF(A50="","",VLOOKUP(A50,'STOCK CONTROL SHEET'!Details,3,FALSE)) -> NO | D50: =INDEX(COMP.STOREPRIMARY,MATCH('STORE PERFORMANCE'!A50,COMPMaterialNo,0),9) | E50: =INDEX(COMP.STOREPRIMARY,MATCH('STORE PERFORMANCE'!A50,COMPMaterialNo,0),10) -> 14
A51: 200066 | B51: =IF(A51="","",VLOOKUP(A51,'STOCK CONTROL SHEET'!Details,2,FALSE)) -> HP Laserjet Tonner 130A (Magenta) | C51: =IF(A51="","",VLOOKUP(A51,'STOCK CONTROL SHEET'!Details,3,FALSE)) -> NO | D51: =INDEX(COMP.STOREPRIMARY,MATCH('STORE PERFORMANCE'!A51,COMPMaterialNo,0),9) | E51: =INDEX(COMP.STOREPRIMARY,MATCH('STORE PERFORMANCE'!A51,COMPMaterialNo,0),10)
A52: 200007 | B52: =IF(A52="","",VLOOKUP(A52,'STOCK CONTROL SHEET'!Details,2,FALSE)) -> HP Laserjet 4600N Tonner (9723A) (Magenta) | C52: =IF(A52="","",VLOOKUP(A52,'STOCK CONTROL SHEET'!Details,3,FALSE)) -> NO | D52: =INDEX(COMP.STOREPRIMARY,MATCH('STORE PERFORMANCE'!A52,COMPMaterialNo,0),9) | E52: =INDEX(COMP.STOREPRIMARY,MATCH('STORE PERFORMANCE'!A52,COMPMaterialNo,0),10)
... A103: 41 | B103: =IF(A103="","",VLOOKUP(A103,'STOCK CONTROL SHEET'!Details,2,FALSE)) -> Tonner Kit TK-8525 (Magenta) | C103: =IF(A103="","",VLOOKUP(A103,'STOCK CONTROL SHEET'!Details,3,FALSE)) -> NO | D103: =INDEX(COMP.STOREPRIMARY,MATCH('STORE PERFORMANCE'!A103,COMPMaterialNo,0),9) | E103: =INDEX(COMP.STOREPRIMARY,MATCH('STORE PERFORMANCE'!A103,COMPMaterialNo,0),10)
A104: MAINTENANCE STORE
A105: Material No | B105: Item Description | C105: Unit of Issue | D105: Quantity Deficit | E105: Quantity Surplus
A106: 282022 | B106: =IF(A106="","",VLOOKUP(A106,'STOCK CONTROL SHEET'!Details,2,FALSE)) -> Air Freshener | C106: =IF(A106="","",VLOOKUP(A106,'STOCK CONTROL SHEET'!Details,3,FALSE)) -> NO | D106: =INDEX(MAINT.STOREPRIMARY,MATCH('STORE PERFORMANCE'!A106,MAINTMaterialNo,0),9) -> 14 | E106: =INDEX(MAINT.STOREPRIMARY,MATCH('STORE PERFORMANCE'!A106,MAINTMaterialNo,0),10)
A107: 282018 | B107: =IF(A107="","",VLOOKUP(A107,'STOCK CONTROL SHEET'!Details,2,FALSE)) -> Bar Soaps | C107: =IF(A107="","",VLOOKUP(A107,'STOCK CONTROL SHEET'!Details,3,FALSE)) -> PCS | D107: =INDEX(MAINT.STOREPRIMARY,MATCH('STORE PERFORMANCE'!A107,MAINTMaterialNo,0),9) | E107: =INDEX(MAINT.STOREPRIMARY,MATCH('STORE PERFORMANCE'!A107,MAINTMaterialNo,0),10) -> 25
A108: 252014 | B108: =IF(A108="","",VLOOKUP(A108,'STOCK CONTROL SHEET'!Details,2,FALSE)) -> 4-Way Extension Socket | C108: =IF(A108="","",VLOOKUP(A108,'STOCK CONTROL SHEET'!Details,3,FALSE)) -> NO | D108: =INDEX(MAINT.STOREPRIMARY,MATCH('STORE PERFORMANCE'!A108,MAINTMaterialNo,0),9) -> 7 | E108: =INDEX(MAINT.STOREPRIMARY,MATCH('STORE PERFORMANCE'!A108,MAINTMaterialNo,0),10)
A109: 252015 | B109: =IF(A109="","",VLOOKUP(A109,'STOCK CONTROL SHEET'!Details,2,FALSE)) -> Single Socket | C109: =IF(A109="","",VLOOKUP(A109,'STOCK CONTROL SHEET'!Details,3,FALSE)) -> NO | D109: =INDEX(MAINT.STOREPRIMARY,MATCH('STORE PERFORMANCE'!A109,MAINTMaterialNo,0),9) | E109: =INDEX(MAINT.STOREPRIMARY,MATCH('STORE PERFORMANCE'!A109,MAINTMaterialNo,0),10)
A110: 100 | B110: =IF(A110="","",VLOOKUP(A110,'STOCK CONTROL SHEET'!Details,2,FALSE)) -> 40 Amp Tap of Unit | C110: =IF(A110="","",VLOOKUP(A110,'STOCK CONTROL SHEET'!Details,3,FALSE)) -> NO | D110: =INDEX(MAINT.STOREPRIMARY,MATCH('STORE PERFORMANCE'!A110,MAINTMaterialNo,0),9) | E110: =INDEX(MAINT.STOREPRIMARY,MATCH('STORE PERFORMANCE'!A110,MAINTMaterialNo,0),10)
A111: 101 | B111: =IF(A111="","",VLOOKUP(A111,'STOCK CONTROL SHEET'!Details,2,FALSE)) -> Blower | C111: =IF(A111="","",VLOOKUP(A111,'STOCK CONTROL SHEET'!Details,3,FALSE)) -> NO | D111: =INDEX(MAINT.STOREPRIMARY,MATCH('STORE PERFORMANCE'!A111,MAINTMaterialNo,0),9) | E111: =INDEX(MAINT.STOREPRIMARY,MATCH('STORE PERFORMANCE'!A111,MAINTMaterialNo,0),10)
A112: 252040 | B112: =IF(A112="","",VLOOKUP(A112,'STOCK CONTROL SHEET'!Details,2,FALSE)) -> Chokes 4/6/8 | C112: =IF(A112="","",VLOOKUP(A112,'STOCK CONTROL SHEET'!Details,3,FALSE)) -> NO | D112: =INDEX(MAINT.STOREPRIMARY,MATCH('STORE PERFORMANCE'!A112,MAINTMaterialNo,0),9) | E112: =INDEX(MAINT.STOREPRIMARY,MATCH('STORE PERFORMANCE'!A112,MAINTMaterialNo,0),10)
A113: 272002 | B113: =IF(A113="","",VLOOKUP(A113,'STOCK CONTROL SHEET'!Details,2,FALSE)) -> Disposable Gloves | C113: =IF(A113="","",VLOOKUP(A113,'STOCK CONTROL SHEET'!Details,3,FALSE)) -> PAIRS | D113: =INDEX(MAINT.STOREPRIMARY,MATCH('STORE PERFORMANCE'!A113,MAINTMaterialNo,0),9) -> 177 | E113: =INDEX(MAINT.STOREPRIMARY,MATCH('STORE PERFORMANCE'!A113,MAINTMaterialNo,0),10)
A114: 252028 | B114: =IF(A114="","",VLOOKUP(A114,'STOCK CONTROL SHEET'!Details,2,FALSE)) -> Door Closer | C114: =IF(A114="","",VLOOKUP(A114,'STOCK CONTROL SHEET'!Details,3,FALSE)) -> NO | D114: =INDEX(MAINT.STOREPRIMARY,MATCH('STORE PERFORMANCE'!A114,MAINTMaterialNo,0),9) | E114: =INDEX(MAINT.STOREPRIMARY,MATCH('STORE PERFORMANCE'!A114,MAINTMaterialNo,0),10)
A115: 105 | B115: =IF(A115="","",VLOOKUP(A115,'STOCK CONTROL SHEET'!Details,2,FALSE)) -> Data Cabinet | C115: =IF(A115="","",VLOOKUP(A115,'STOCK CONTROL SHEET'!Details,3,FALSE)) -> NO | D115: =INDEX(MAINT.STOREPRIMARY,MATCH('STORE PERFORMANCE'!A115,MAINTMaterialNo,0),9) -> #VALUE! | E115: =INDEX(MAINT.STOREPRIMARY,MATCH('STORE PERFORMANCE'!A115,MAINTMaterialNo,0),10) -> #VALUE!
A116: 282030 | B116: =IF(A116="","",VLOOKUP(A116,'STOCK CONTROL SHEET'!Details,2,FALSE)) -> Duster Washing Pads | C116: =IF(A116="","",VLOOKUP(A116,'STOCK CONTROL SHEET'!Details,3,FALSE)) -> NO | D116: =INDEX(MAINT.STOREPRIMARY,MATCH('STORE PERFORMANCE'!A116,MAINTMaterialNo,0),9) | E116: =INDEX(MAINT.STOREPRIMARY,MATCH('STORE PERFORMANCE'!A116,MAINTMaterialNo,0),10)
A117: 252001 | B117: =IF(A117="","",VLOOKUP(A117,'STOCK CONTROL SHEET'!Details,2,FALSE)) -> Aluminium Door Locks | C117: =IF(A117="","",VLOOKUP(A117,'STOCK CONTROL SHEET'!Details,3,FALSE)) -> NO | D117: =INDEX(MAINT.STOREPRIMARY,MATCH('STORE PERFORMANCE'!A117,MAINTMaterialNo,0),9) | E117: =INDEX(MAINT.STOREPRIMARY,MATCH('STORE PERFORMANCE'!A117,MAINTMaterialNo,0),10)
... A151: 252017 | B151: =IF(A151="","",VLOOKUP(A151,'STOCK CONTROL SHEET'!Details,2,FALSE)) -> Toilet Seat Covers | C151: =IF(A151="","",VLOOKUP(A151,'STOCK CONTROL SHEET'!Details,3,FALSE)) -> NO | D151: =INDEX(MAINT.STOREPRIMARY,MATCH('STORE PERFORMANCE'!A151,MAINTMaterialNo,0),9) | E151: =INDEX(MAINT.STOREPRIMARY,MATCH('STORE PERFORMANCE'!A151,MAINTMaterialNo,0),10) -> 2

Sheet SF STORE
A1: INVENTORY IN&OUT SCHEDULE
A2: Date | B2: Document No | C2: Type | D2: Material No | E2: Item Description | F2: Unit of Issue | G2: In&Out Qty | H2: Department | I2: Running Balance
A3: 45842 | B3: 490002787 | C3: Issue | D3: 100143 | E3: =IF(D3="","",VLOOKUP(D3,'STOCK CONTROL SHEET'!Details,2,FALSE)) -> Laminating Pouches | F3: =IF(D3="","",VLOOKUP(D3,'STOCK CONTROL SHEET'!Details,3,FALSE)) -> PCS | G3: 100 | H3: KIAMBU | I3: =IF(UnitsTable[Type]="Receipt",(SUM(UnitsTable[[#This Row],[In&Out Qty]])),(SUM(-INOUTQTY))) -> -100
A4: 45842 | B4: 4900027277 | C4: Issue | D4: 100220 | E4: =IF(D4="","",VLOOKUP(D4,'STOCK CONTROL SHEET'!Details,2,FALSE)) -> Payment of Benefit Forms/004 | F4: =IF(D4="","",VLOOKUP(D4,'STOCK CONTROL SHEET'!Details,3,FALSE)) -> PCS | G4: 500 | H4: KAKAMEGA | I4: =IF(UnitsTable[Type]="Receipt",(SUM(UnitsTable[[#This Row],[In&Out Qty]])),(SUM(-INOUTQTY))) -> -500 | M4: Issue | N4: EA
A5: 45842 | B5: 4900027277 | C5: Issue | D5: 100139 | E5: =IF(D5="","",VLOOKUP(D5,'STOCK CONTROL SHEET'!Details,2,FALSE)) -> App. For Employer SF/001 | F5: =IF(D5="","",VLOOKUP(D5,'STOCK CONTROL SHEET'!Details,3,FALSE)) -> PCS | G5: 500 | H5: KAKAMEGA | I5: =IF(UnitsTable[Type]="Receipt",(SUM(UnitsTable[[#This Row],[In&Out Qty]])),(SUM(-INOUTQTY))) -> -500 | M5: Receipt | N5: NO
A6: 45842 | B6: 4900027277 | C6: Issue | D6: 100218 | E6: =IF(D6="","",VLOOKUP(D6,'STOCK CONTROL SHEET'!Details,2,FALSE)) -> Ben. App. Forms SF/001 | F6: =IF(D6="","",VLOOKUP(D6,'STOCK CONTROL SHEET'!Details,3,FALSE)) -> PCS | G6: 300 | H6: KAKAMEGA | I6: =IF(UnitsTable[Type]="Receipt",(SUM(UnitsTable[[#This Row],[In&Out Qty]])),(SUM(-INOUTQTY))) -> -300 | M6: Loaned | N6: PAC
A7: 45842 | B7: 4900027277 | C7: Issue | D7: 100138 | E7: =IF(D7="","",VLOOKUP(D7,'STOCK CONTROL SHEET'!Details,2,FALSE)) -> Fingerprint Forms SF/003 | F7: =IF(D7="","",VLOOKUP(D7,'STOCK CONTROL SHEET'!Details,3,FALSE)) -> PCS | G7: 500 | H7: KAKAMEGA | I7: =IF(UnitsTable[Type]="Receipt",(SUM(UnitsTable[[#This Row],[In&Out Qty]])),(SUM(-INOUTQTY))) -> -500 | N7: PCS
A8: 45842 | B8: 4900027277 | C8: Issue | D8: 100145 | E8: =IF(D8="","",VLOOKUP(D8,'STOCK CONTROL SHEET'!Details,2,FALSE)) -> Membership Cards (Blank) | F8: =IF(D8="","",VLOOKUP(D8,'STOCK CONTROL SHEET'!Details,3,FALSE)) -> PCS | G8: 3000 | H8: KAKAMEGA | I8: =IF(UnitsTable[Type]="Receipt",(SUM(UnitsTable[[#This Row],[In&Out Qty]])),(SUM(-INOUTQTY))) -> -3000 | N8: PKT
A9: 45842 | B9: 4900027277 | C9: Issue | D9: 100213 | E9: =IF(D9="","",VLOOKUP(D9,'STOCK CONTROL SHEET'!Details,2,FALSE)) -> Schedule of Contribution | F9: =IF(D9="","",VLOOKUP(D9,'STOCK CONTROL SHEET'!Details,3,FALSE)) -> PCS | G9: 1000 | H9: KAKAMEGA | I9: =IF(UnitsTable[Type]="Receipt",(SUM(UnitsTable[[#This Row],[In&Out Qty]])),(SUM(-INOUTQTY))) -> -1000 | N9: RM
A10: 45842 | B10: 4900027277 | C10: Issue | D10: 100211 | E10: =IF(D10="","",VLOOKUP(D10,'STOCK CONTROL SHEET'!Details,2,FALSE)) -> Survivor Ben. Form | F10: =IF(D10="","",VLOOKUP(D10,'STOCK CONTROL SHEET'!Details,3,FALSE)) -> PCS | G10: 100 | H10: KAKAMEGA | I10: =IF(UnitsTable[Type]="Receipt",(SUM(UnitsTable[[#This Row],[In&Out Qty]])),(SUM(-INOUTQTY))) -> -100 | N10: ROLL
A11: 45842 | B11: 4900027277 | C11: Issue | D11: 100220 | E11: =IF(D11="","",VLOOKUP(D11,'STOCK CONTROL SHEET'!Details,2,FALSE)) -> Payment of Benefit Forms/004 | F11: =IF(D11="","",VLOOKUP(D11,'STOCK CONTROL SHEET'!Details,3,FALSE)) -> PCS | G11: 500 | H11: KAKAMEGA | I11: =IF(UnitsTable[Type]="Receipt",(SUM(UnitsTable[[#This Row],[In&Out Qty]])),(SUM(-INOUTQTY))) -> -500 | N11: TUBE
A12: 45842 | B12: 4900027282 | C12: Issue | D12: 100218 | E12: =IF(D12="","",VLOOKUP(D12,'STOCK CONTROL SHEET'!Details,2,FALSE)) -> Ben. App. Forms SF/001 | F12: =IF(D12="","",VLOOKUP(D12,'STOCK CONTROL SHEET'!Details,3,FALSE)) -> PCS | G12: 500 | H12: ELDORET | I12: =IF(UnitsTable[Type]="Receipt",(SUM(UnitsTable[[#This Row],[In&Out Qty]])),(SUM(-INOUTQTY))) -> -500
A13: 45842 | B13: 4900027282 | C13: Issue | D13: 100138 | E13: =IF(D13="","",VLOOKUP(D13,'STOCK CONTROL SHEET'!Details,2,FALSE)) -> Fingerprint Forms SF/003 | F13: =IF(D13="","",VLOOKUP(D13,'STOCK CONTROL SHEET'!Details,3,FALSE)) -> PCS | G13: 500 | H13: ELDORET | I13: =IF(UnitsTable[Type]="Receipt",(SUM(UnitsTable[[#This Row],[In&Out Qty]])),(SUM(-INOUTQTY))) -> -500
A14: 45842 | B14: 4900027282 | C14: Issue | D14: 100211 | E14: =IF(D14="","",VLOOKUP(D14,'STOCK CONTROL SHEET'!Details,2,FALSE)) -> Survivor Ben. Form | F14: =IF(D14="","",VLOOKUP(D14,'STOCK CONTROL SHEET'!Details,3,FALSE)) -> PCS | G14: 200 | H14: ELDORET | I14: =IF(UnitsTable[Type]="Receipt",(SUM(UnitsTable[[#This Row],[In&Out Qty]])),(SUM(-INOUTQTY))) -> -200
A15: 45842 | B15: 4900027282 | C15: Issue | D15: 100143 | E15: =IF(D15="","",VLOOKUP(D15,'STOCK CONTROL SHEET'!Details,2,FALSE)) -> Laminating Pouches | F15: =IF(D15="","",VLOOKUP(D15,'STOCK CONTROL SHEET'!Details,3,FALSE)) -> PCS | G15: 2000 | H15: ELDORET | I15: =IF(UnitsTable[Type]="Receipt",(SUM(UnitsTable[[#This Row],[In&Out Qty]])),(SUM(-INOUTQTY))) -> -2000
A16: 45842 | B16: 4900027282 | C16: Issue | D16: 100181 | E16: =IF(D16="","",VLOOKUP(D16,'STOCK CONTROL SHEET'!Details,2,FALSE)) -> Registration Gen. Folders | F16: =IF(D16="","",VLOOKUP(D16,'STOCK CONTROL SHEET'!Details,3,FALSE)) -> PCS | G16: 300 | H16: ELDORET | I16: =IF(UnitsTable[Type]="Receipt",(SUM(UnitsTable[[#This Row],[In&Out Qty]])),(SUM(-INOUTQTY))) -> -300
A17: 45842 | B17: 4900027282 | C17: Issue | D17: 100145 | E17: =IF(D17="","",VLOOKUP(D17,'STOCK CONTROL SHEET'!Details,2,FALSE)) -> Membership Cards (Blank) | F17: =IF(D17="","",VLOOKUP(D17,'STOCK CONTROL SHEET'!Details,3,FALSE)) -> PCS | G17: 3000 | H17: ELDORET | I17: =IF(UnitsTable[Type]="Receipt",(SUM(UnitsTable[[#This Row],[In&Out Qty]])),(SUM(-INOUTQTY))) -> -3000
A18: 45842 | B18: 4900027285 | C18: Issue | D18: 100138 | E18: =IF(D18="","",VLOOKUP(D18,'STOCK CONTROL SHEET'!Details,2,FALSE)) -> Fingerprint Forms SF/003 | F18: =IF(D18="","",VLOOKUP(D18,'STOCK CONTROL SHEET'!Details,3,FALSE)) -> PCS | G18: 500 | H18: KIAMBU | I18: =IF(UnitsTable[Type]="Receipt",(SUM(UnitsTable[[#This Row],[In&Out Qty]])),(SUM(-INOUTQTY))) -> -500
A19: 45842 | B19: 4900027285 | C19: Issue | D19: 100220 | E19: =IF(D19="","",VLOOKUP(D19,'STOCK CONTROL SHEET'!Details,2,FALSE)) -> Payment of Benefit Forms/004 | F19: =IF(D19="","",VLOOKUP(D19,'STOCK CONTROL SHEET'!Details,3,FALSE)) -> PCS | G19: 400 | H19: KIAMBU | I19: =IF(UnitsTable[Type]="Receipt",(SUM(UnitsTable[[#This Row],[In&Out Qty]])),(SUM(-INOUTQTY))) -> -400
A20: 45842 | B20: 4900027285 | C20: Issue | D20: 100139 | E20: =IF(D20="","",VLOOKUP(D20,'STOCK CONTROL SHEET'!Details,2,FALSE)) -> App. For Employer SF/001 | F20: =IF(D20="","",VLOOKUP(D20,'STOCK CONTROL SHEET'!Details,3,FALSE)) -> PCS | G20: 500 | H20: KIAMBU | I20: =IF(UnitsTable[Type]="Receipt",(SUM(UnitsTable[[#This Row],[In&Out Qty]])),(SUM(-INOUTQTY))) -> -500
A21: 45842 | B21: 4900027285 | C21: Issue | D21: 100181 | E21: =IF(D21="","",VLOOKUP(D21,'STOCK CONTROL SHEET'!Details,2,FALSE)) -> Registration Gen. Folders | F21: =IF(D21="","",VLOOKUP(D21,'STOCK CONTROL SHEET'!Details,3,FALSE)) -> PCS | G21: 200 | H21: KIAMBU | I21: =IF(UnitsTable[Type]="Receipt",(SUM(UnitsTable[[#This Row],[In&Out Qty]])),(SUM(-INOUTQTY))) -> -200
A22: 45842 | B22: 4900027280 | C22: Issue | D22: 100145 | E22: =IF(D22="","",VLOOKUP(D22,'STOCK CONTROL SHEET'!Details,2,FALSE)) -> Membership Cards (Blank) | F22: =IF(D22="","",VLOOKUP(D22,'STOCK CONTROL SHEET'!Details,3,FALSE)) -> PCS | G22: 3000 | H22: MOMBASA | I22: =IF(UnitsTable[Type]="Receipt",(SUM(UnitsTable[[#This Row],[In&Out Qty]])),(SUM(-INOUTQTY))) -> -3000
A23: 45842 | B23: 4900027280 | C23: Issue | D23: 100143 | E23: =IF(D23="","",VLOOKUP(D23,'STOCK CONTROL SHEET'!Details,2,FALSE)) -> Laminating Pouches | F23: =IF(D23="","",VLOOKUP(D23,'STOCK CONTROL SHEET'!Details,3,FALSE)) -> PCS | G23: 3000 | H23: MOMBASA | I23: =IF(UnitsTable[Type]="Receipt",(SUM(UnitsTable[[#This Row],[In&Out Qty]])),(SUM(-INOUTQTY))) -> -3000
... A123: 45862 | B123: 4900027468 | C123: Receipt | D123: 100143 | E123: =IF(D123="","",VLOOKUP(D123,'STOCK CONTROL SHEET'!Details,2,FALSE)) -> Laminating Pouches | F123: =IF(D123="","",VLOOKUP(D123,'STOCK CONTROL SHEET'!Details,3,FALSE)) -> PCS | G123: 2000 | H123: INDUSTRIAL AREA | I123: =IF(UnitsTable[Type]="Receipt",(SUM(UnitsTable[[#This Row],[In&Out Qty]])),(SUM(-INOUTQTY))) -> 2000

Sheet SF REPORT
A1: SUPPLY CHAIN DEPARTMENT
A2: SF STORE REPORT
A3: Sum of In&Out Qty | B3: Column Labels
A4: Row Labels | B4: Issue | C4: Receipt | D4: Grand Total
A5: 45842 | B5: 21900 | D5: 21900
A6: PCS | B6: 21900 | D6: 21900
A7: App. For Employer SF/001 | B7: 1000 | D7: 1000
A8: KAKAMEGA | B8: 500 | D8: 500
A9: KIAMBU | B9: 500 | D9: 500
A10: Ben. App. Forms SF/001 | B10: 800 | D10: 800
A11: ELDORET | B11: 500 | D11: 500
A12: KAKAMEGA | B12: 300 | D12: 300
A13: Laminating Pouches | B13: 5100 | D13: 5100
A14: ELDORET | B14: 2000 | D14: 2000
A15: KIAMBU | B15: 100 | D15: 100
A16: MOMBASA | B16: 3000 | D16: 3000
A17: Membership Cards (Blank) | B17: 9000 | D17: 9000
... A40: MOMBASA | B40: 100 | D40: 100
A41: 45846 | B41: 7000 | D41: 7000
A42: PCS | B42: 7000 | D42: 7000
A43: App. For Employer SF/001 | B43: 500 | D43: 500
A44: CITY CENTRE | B44: 500 | D44: 500
A45: Laminating Pouches | B45: 3000 | D45: 3000
A46: CITY CENTRE | B46: 3000 | D46: 3000
A47: Membership Cards (Blank) | B47: 3000 | D47: 3000
A48: CITY CENTRE | B48: 3000 | D48: 3000
A49: Fingerprint Forms SF/003 | B49: 500 | D49: 500
A50: CITY CENTRE | B50: 500 | D50: 500
A51: 45847 | B51: 8030 | D51: 8030
A52: PCS | B52: 8030 | D52: 8030
A53: Ben. App. Forms SF/001 | B53: 150 | D53: 150
A54: MTWAPA | B54: 150 | D54: 150
A55: Laminating Pouches | B55: 2000 | D55: 2000
A56: MTWAPA | B56: 2000 | D56: 2000
A57: Membership Cards (Blank) | B57: 5000 | D57: 5000
A58: KIAMBU | B58: 3000 | D58: 3000
A59: MTWAPA | B59: 2000 | D59: 2000
A60: Payment of Benefit Forms/004 | B60: 100 | D60: 100
A61: MTWAPA | B61: 100 | D61: 100
A62: Survivor Ben. Form | B62: 200 | D62: 200
A63: MTWAPA | B63: 200 | D63: 200
... A67: MTWAPA | B67: 80 | D67: 80
A68: 45849 | B68: 10200 | D68: 10200
A69: PCS | B69: 10200 | D69: 10200
A70: App. For Employer SF/001 | B70: 500 | D70: 500
A71: KITENGELA | B71: 500 | D71: 500
A72: Ben. App. Forms SF/001 | B72: 700 | D72: 700
A73: HOMABAY | B73: 300 | D73: 300
A74: KITENGELA | B74: 400 | D74: 400
A75: Envelopes A4 | B75: 200 | D75: 200
A76: FINANCE | B76: 200 | D76: 200
A77: Envelopes A5 | B77: 200 | D77: 200
A78: FINANCE | B78: 200 | D78: 200
A79: Laminating Pouches | B79: 3000 | D79: 3000
A80: KITENGELA | B80: 3000 | D80: 3000
... A94: HOMABAY | B94: 100 | D94: 100
A95: 45852 | B95: 6300 | D95: 6300
A96: PCS | B96: 6300 | D96: 6300
A97: App. For Employer SF/001 | B97: 500 | D97: 500
A98: THIKA | B98: 500 | D98: 500
A99: Ben. App. Forms SF/001 | B99: 500 | D99: 500
A100: THIKA | B100: 500 | D100: 500
A101: Envelopes A4 | B101: 300 | D101: 300
A102: STRATEGY & CHANGE | B102: 300 | D102: 300
A103: Laminating Pouches | B103: 4000 | D103: 4000
A104: THIKA | B104: 4000 | D104: 4000
A105: Payment of Benefit Forms/004 | B105: 500 | D105: 500
A106: THIKA | B106: 500 | D106: 500
A107: Registration Gen. Folders | B107: 300 | D107: 300
... A110: THIKA | B110: 200 | D110: 200
A111: 45853 | B111: 3860 | D111: 3860
A112: PCS | B112: 3860 | D112: 3860
A113: Envelopes A3 (16*12) White | B113: 200 | D113: 200
A114: REGISTRATION & COMPLIANCE | B114: 200 | D114: 200
A115: Envelopes A4 | B115: 1300 | D115: 1300
A116: GM HR/ADM | B116: 500 | D116: 500
A117: HR TALENT ACQUISITION | B117: 500 | D117: 500
A118: PROPERTY DEVELOPMENT | B118: 100 | D118: 100
A119: REGISTRATION & COMPLIANCE | B119: 200 | D119: 200
A120: Envelopes A5 | B120: 1300 | D120: 1300
A121: GM HR/ADM | B121: 500 | D121: 500
A122: HR TALENT ACQUISITION | B122: 500 | D122: 500
A123: HUMAN CAPITAL/HR | B123: 200 | D123: 200
... A128: HUMAN CAPITAL/HR | B128: 60 | D128: 60
A129: 45854 | B129: 210 | D129: 210
A130: PCS | B130: 210 | D130: 210
A131: Envelopes A3 (16*12) White | B131: 50 | D131: 50
A132: PROPERTY MANAGEMENT | B132: 50 | D132: 50
A133: Envelopes A4 | B133: 100 | D133: 100
A134: ETHICS & INTEGRITY | B134: 100 | D134: 100
A135: Envelopes A5 | B135: 60 | D135: 60
A136: ETHICS & INTEGRITY | B136: 50 | D136: 50
A137: PROPERTY MANAGEMENT | B137: 10 | D137: 10
A138: 45855 | B138: 10300 | D138: 10300
A139: PCS | B139: 10300 | D139: 10300
A140: App. For Employer SF/001 | B140: 1000 | D140: 1000
A141: CITY CENTRE | B141: 500 | D141: 500
A142: UKUNDA | B142: 500 | D142: 500
A143: Ben. App. Forms SF/001 | B143: 400 | D143: 400
A144: UKUNDA | B144: 400 | D144: 400
...

Sheet COMPUTER STORE
A1: INVENTORY IN&OUT SCHEDULE
A2: Date | B2: Document No | C2: Type | D2: Material No | E2: Item Description | F2: Unit of Issue | G2: In&Out Qty | H2: Department | I2: Running Balance
A3: 45928 | B3: 4900056778 | C3: Issue | D3: 100172 | E3: =IF(D3="","",VLOOKUP(D3,'STOCK CONTROL SHEET'!Details,2,FALSE)) -> 1 Part Statement Paper | F3: =IF(D3="","",VLOOKUP(D3,'STOCK CONTROL SHEET'!Details,3,FALSE)) -> PCS | G3: 1000 | H3: ISIOLO | I3: =IF(ComputerStoreUnitsTable[Type]="Receipt",(SUM(ComputerStoreUnitsTable[[#This Row],[In&Out Qty]])),(SUM(-INOUTQTY))) -> -1000
E4: =IF(D4="","",VLOOKUP(D4,'STOCK CONTROL SHEET'!Details,2,FALSE)) | F4: =IF(D4="","",VLOOKUP(D4,'STOCK CONTROL SHEET'!Details,3,FALSE)) | I4: =IF(ComputerStoreUnitsTable[Type]="Receipt",(SUM(ComputerStoreUnitsTable[[#This Row],[In&Out Qty]])),(SUM(-INOUTQTY))) -> 0 | M4: Issue | N4: EA
E5: =IF(D5="","",VLOOKUP(D5,'STOCK CONTROL SHEET'!Details,2,FALSE)) | F5: =IF(D5="","",VLOOKUP(D5,'STOCK CONTROL SHEET'!Details,3,FALSE)) | I5: =IF(ComputerStoreUnitsTable[Type]="Receipt",(SUM(ComputerStoreUnitsTable[[#This Row],[In&Out Qty]])),(SUM(-INOUTQTY))) -> 0 | M5: Receipt | N5: NO
E6: =IF(D6="","",VLOOKUP(D6,'STOCK CONTROL SHEET'!Details,2,FALSE)) | F6: =IF(D6="","",VLOOKUP(D6,'STOCK CONTROL SHEET'!Details,3,FALSE)) | I6: =IF(ComputerStoreUnitsTable[Type]="Receipt",(SUM(ComputerStoreUnitsTable[[#This Row],[In&Out Qty]])),(SUM(-INOUTQTY))) -> 0 | M6: Loaned | N6: PAC
E7: =IF(D7="","",VLOOKUP(D7,'STOCK CONTROL SHEET'!Details,2,FALSE)) | F7: =IF(D7="","",VLOOKUP(D7,'STOCK CONTROL SHEET'!Details,3,FALSE)) | I7: =IF(ComputerStoreUnitsTable[Type]="Receipt",(SUM(ComputerStoreUnitsTable[[#This Row],[In&Out Qty]])),(SUM(-INOUTQTY))) -> 0 | N7: PCS
E8: =IF(D8="","",VLOOKUP(D8,'STOCK CONTROL SHEET'!Details,2,FALSE)) | F8: =IF(D8="","",VLOOKUP(D8,'STOCK CONTROL SHEET'!Details,3,FALSE)) | I8: =IF(ComputerStoreUnitsTable[Type]="Receipt",(SUM(ComputerStoreUnitsTable[[#This Row],[In&Out Qty]])),(SUM(-INOUTQTY))) -> 0 | N8: PKT
E9: =IF(D9="","",VLOOKUP(D9,'STOCK CONTROL SHEET'!Details,2,FALSE)) | F9: =IF(D9="","",VLOOKUP(D9,'STOCK CONTROL SHEET'!Details,3,FALSE)) | I9: =IF(ComputerStoreUnitsTable[Type]="Receipt",(SUM(ComputerStoreUnitsTable[[#This Row],[In&Out Qty]])),(SUM(-INOUTQTY))) -> 0 | N9: RM
E10: =IF(D10="","",VLOOKUP(D10,'STOCK CONTROL SHEET'!Details,2,FALSE)) | F10: =IF(D10="","",VLOOKUP(D10,'STOCK CONTROL SHEET'!Details,3,FALSE)) | I10: =IF(ComputerStoreUnitsTable[Type]="Receipt",(SUM(ComputerStoreUnitsTable[[#This Row],[In&Out Qty]])),(SUM(-INOUTQTY))) -> 0 | N10: ROLL
E11: =IF(D11="","",VLOOKUP(D11,'STOCK CONTROL SHEET'!Details,2,FALSE)) | F11: =IF(D11="","",VLOOKUP(D11,'STOCK CONTROL SHEET'!Details,3,FALSE)) | I11: =IF(ComputerStoreUnitsTable[Type]="Receipt",(SUM(ComputerStoreUnitsTable[[#This Row],[In&Out Qty]])),(SUM(-INOUTQTY))) -> 0 | N11: TUBE

Sheet COMPUTER REPORT
A1: SUPPLY CHAIN DEPARTMENT
A2: COMPUTER STORE REPORT
A3: Sum of In&Out Qty | B3: Column Labels
A4: Row Labels | B4: Issue | C4: Grand Total
A5: 45928 | B5: 1000 | C5: 1000
A6: PCS | B6: 1000 | C6: 1000
A7: 1 Part Statement Paper | B7: 1000 | C7: 1000
A8: ISIOLO | B8: 1000 | C8: 1000
A9: Grand Total | B9: 1000 | C9: 1000

Sheet MAINTENANCE
A1: INVENTORY IN&OUT SCHEDULE
A2: Date | B2: Document No | C2: Type | D2: Material No | E2: Item Description | F2: Unit of Issue | G2: In&Out Qty | H2: Department | I2: Running Balance
C3: Issue | D3: 105 | E3: =IF(D3="","",VLOOKUP(D3,'STOCK CONTROL SHEET'!Details,2,FALSE)) -> Data Cabinet | F3: =IF(D3="","",VLOOKUP(D3,'STOCK CONTROL SHEET'!Details,3,FALSE)) -> NO | G3: 20 | H3: NAROK | I3: =IF(MAINTENANCEUnitsTable[Type]="Receipt",(SUM(MAINTENANCEUnitsTable[[#This Row],[In&Out Qty]])),(SUM(-INOUTQTY))) -> -20
E4: =IF(D4="","",VLOOKUP(D4,'STOCK CONTROL SHEET'!Details,2,FALSE)) | F4: =IF(D4="","",VLOOKUP(D4,'STOCK CONTROL SHEET'!Details,3,FALSE)) | I4: =IF(MAINTENANCEUnitsTable[Type]="Receipt",(SUM(MAINTENANCEUnitsTable[[#This Row],[In&Out Qty]])),(SUM(-INOUTQTY))) -> 0 | M4: Issue | N4: EA
E5: =IF(D5="","",VLOOKUP(D5,'STOCK CONTROL SHEET'!Details,2,FALSE)) | F5: =IF(D5="","",VLOOKUP(D5,'STOCK CONTROL SHEET'!Details,3,FALSE)) | I5: =IF(MAINTENANCEUnitsTable[Type]="Receipt",(SUM(MAINTENANCEUnitsTable[[#This Row],[In&Out Qty]])),(SUM(-INOUTQTY))) -> 0 | M5: Receipt | N5: NO
E6: =IF(D6="","",VLOOKUP(D6,'STOCK CONTROL SHEET'!Details,2,FALSE)) | F6: =IF(D6="","",VLOOKUP(D6,'STOCK CONTROL SHEET'!Details,3,FALSE)) | I6: =IF(MAINTENANCEUnitsTable[Type]="Receipt",(SUM(MAINTENANCEUnitsTable[[#This Row],[In&Out Qty]])),(SUM(-INOUTQTY))) -> 0 | M6: Loaned | N6: PAC
E7: =IF(D7="","",VLOOKUP(D7,'STOCK CONTROL SHEET'!Details,2,FALSE)) | F7: =IF(D7="","",VLOOKUP(D7,'STOCK CONTROL SHEET'!Details,3,FALSE)) | I7: =IF(MAINTENANCEUnitsTable[Type]="Receipt",(SUM(MAINTENANCEUnitsTable[[#This Row],[In&Out Qty]])),(SUM(-INOUTQTY))) -> 0 | N7: PCS
E8: =IF(D8="","",VLOOKUP(D8,'STOCK CONTROL SHEET'!Details,2,FALSE)) | F8: =IF(D8="","",VLOOKUP(D8,'STOCK CONTROL SHEET'!Details,3,FALSE)) | I8: =IF(MAINTENANCEUnitsTable[Type]="Receipt",(SUM(MAINTENANCEUnitsTable[[#This Row],[In&Out Qty]])),(SUM(-INOUTQTY))) -> 0 | N8: PKT
E9: =IF(D9="","",VLOOKUP(D9,'STOCK CONTROL SHEET'!Details,2,FALSE)) | F9: =IF(D9="","",VLOOKUP(D9,'STOCK CONTROL SHEET'!Details,3,FALSE)) | I9: =IF(MAINTENANCEUnitsTable[Type]="Receipt",(SUM(MAINTENANCEUnitsTable[[#This Row],[In&Out Qty]])),(SUM(-INOUTQTY))) -> 0 | N9: RM
E10: =IF(D10="","",VLOOKUP(D10,'STOCK CONTROL SHEET'!Details,2,FALSE)) | F10: =IF(D10="","",VLOOKUP(D10,'STOCK CONTROL SHEET'!Details,3,FALSE)) | I10: =IF(MAINTENANCEUnitsTable[Type]="Receipt",(SUM(MAINTENANCEUnitsTable[[#This Row],[In&Out Qty]])),(SUM(-INOUTQTY))) -> 0 | N10: ROLL
E11: =IF(D11="","",VLOOKUP(D11,'STOCK CONTROL SHEET'!Details,2,FALSE)) | F11: =IF(D11="","",VLOOKUP(D11,'STOCK CONTROL SHEET'!Details,3,FALSE)) | I11: =IF(MAINTENANCEUnitsTable[Type]="Receipt",(SUM(MAINTENANCEUnitsTable[[#This Row],[In&Out Qty]])),(SUM(-INOUTQTY))) -> 0 | N11: TUBE

Sheet MAINTENANCE REPORT
A1: SUPPLY CHAIN DEPARTMENT
A2: MAINTENANCE STORE REPORT
A3: Row Labels | B3: Sum of In&Out Qty
A4: (blank) | B4: 20
A6: (blank)
A7: (blank)
A8: Data Cabinet | B8: 20
A9: Issue | B9: 20
A10: NAROK | B10: 20
A11: Grand Total | B11: 20

Sheet AVERAGE CONSUMPTION
A6: Average of In&Out Qty | B6: Column Labels
A7: Item Description | B7: Issue | C7: Receipt | D7: Grand Total
A8: Membership Cards (Blank) | B8: 2750 | C8: 1000 | D8: 2647.0588
A9: CITY CENTRE | B9: 3000 | D9: 3000
A10: UKUNDA | B10: 2000 | D10: 2000
A11: MACHAKOS | B11: 1000 | D11: 1000
A12: HILL BRANCH | B12: 4000 | D12: 4000
A13: MOMBASA | B13: 3000 | D13: 3000
A14: KAKAMEGA | B14: 3000 | D14: 3000
A15: KIAMBU | B15: 3000 | D15: 3000
A16: ELDORET | B16: 3000 | D16: 3000
A17: MTWAPA | B17: 2000 | D17: 2000
A18: KITENGELA | B18: 3000 | D18: 3000
A19: REGISTRATION & COMPLIANCE | B19: 1000 | D19: 1000
A20: INDUSTRIAL AREA | C20: 1000 | D20: 1000
A21: DONHOLM | B21: 3000 | D21: 3000
A22: NAKURU | B22: 6000 | D22: 6000
A23: KITUI | B23: 1000 | D23: 1000
A24: Laminating Pouches | B24: 2425 | C24: 2000 | D24: 2392.3077
A25: THIKA | B25: 4000 | D25: 4000
A26: CITY CENTRE | B26: 3000 | D26: 3000
A27: MACHAKOS | B27: 2000 | D27: 2000
A28: HILL BRANCH | B28: 2000 | D28: 2000
A29: MOMBASA | B29: 3000 | D29: 3000
A30: KIAMBU | B30: 100 | D30: 100
A31: ELDORET | B31: 2000 | D31: 2000
A32: MTWAPA | B32: 2000 | D32: 2000
A33: KITENGELA | B33: 3000 | D33: 3000
A34: INDUSTRIAL AREA | C34: 2000 | D34: 2000
A35: DONHOLM | B35: 3000 | D35: 3000
A36: NAKURU | B36: 2000 | D36: 2000
A37: Schedule of Contribution | B37: 1000 | D37: 1000
A38: KAKAMEGA | B38: 1000 | D38: 1000
A39: Fingerprint Forms SF/003 | B39: 500 | D39: 500
A40: CITY CENTRE | B40: 500 | D40: 500
A41: MOMBASA | B41: 500 | D41: 500
A42: KAKAMEGA | B42: 500 | D42: 500
A43: KIAMBU | B43: 500 | D43: 500
A44: ELDORET | B44: 500 | D44: 500
A45: MTWAPA | B45: 500 | D45: 500
A46: HOMABAY | B46: 500 | D46: 500
... A55: KITENGELA | B55: 500 | D55: 500
A56: Payment of Benefit Forms/004 | B56: 446.15385 | C56: 500 | D56: 450
A57: WESTLANDS | B57: 500 | D57: 500
A58: THIKA | B58: 500 | D58: 500
A59: MACHAKOS | B59: 500 | D59: 500
A60: HILL BRANCH | B60: 500 | D60: 500
A61: MOMBASA | B61: 500 | D61: 500
A62: KAKAMEGA | B62: 500 | D62: 500
A63: KIAMBU | B63: 400 | D63: 400
A64: EASTLEIGH | B64: 300 | D64: 300
A65: MTWAPA | B65: 100 | D65: 100
A66: HOMABAY | B66: 500 | D66: 500
A67: KITENGELA | B67: 500 | D67: 500
A68: INDUSTRIAL AREA | C68: 500 | D68: 500
A69: NAKURU | B69: 500 | D69: 500
A70: Ben. App. Forms SF/001 | B70: 390 | D70: 390
A71: WESTLANDS | B71: 400 | D71: 400
A72: THIKA | B72: 500 | D72: 500
A73: UKUNDA | B73: 400 | D73: 400
A74: MACHAKOS | B74: 300 | D74: 300
A75: HILL BRANCH | B75: 500 | D75: 500
A76: KAKAMEGA | B76: 300 | D76: 300
A77: KIAMBU | B77: 300 | D77: 300
A78: ELDORET | B78: 500 | D78: 500
A79: EASTLEIGH | B79: 300 | D79: 300
A80: MTWAPA | B80: 150 | D80: 150
... A137: NAKURU | B137: 20 | D137: 20
A138: Grand Total | B138: 870.9322 | C138: 1166.6667 | D138: 878.26446

Sheet MAX CONSUMPTION
A4: Type | B4: (All)
A6: Row Labels | B6: Max of In&Out Qty
A7: Membership Cards (Blank) | B7: 6000
A8: CITY CENTRE | B8: 3000
A9: 45846 | B9: 3000
A10: 45855 | B10: 3000
A11: UKUNDA | B11: 2000
A12: 45855 | B12: 2000
A13: MACHAKOS | B13: 1000
A14: 45859 | B14: 1000
A15: HILL BRANCH | B15: 4000
A16: 45860 | B16: 4000
A17: MOMBASA | B17: 3000
A18: 45842 | B18: 3000
A19: 45856 | B19: 3000
A20: KAKAMEGA | B20: 3000
A21: 45842 | B21: 3000
A22: KIAMBU | B22: 3000
A23: 45847 | B23: 3000
A24: ELDORET | B24: 3000
A25: 45842 | B25: 3000
A26: MTWAPA | B26: 2000
A27: 45847 | B27: 2000
A28: KITENGELA | B28: 3000
A29: 45849 | B29: 3000
A30: REGISTRATION & COMPLIANCE | B30: 1000
A31: 45853 | B31: 1000
A32: INDUSTRIAL AREA | B32: 1000
A33: 45862 | B33: 1000
A34: DONHOLM | B34: 3000
A35: 45860 | B35: 3000
A36: NAKURU | B36: 6000
A37: 45860 | B37: 6000
A38: KITUI | B38: 1000
A39: 45861 | B39: 1000
A40: Laminating Pouches | B40: 4000
A41: THIKA | B41: 4000
A42: 45852 | B42: 4000
A43: CITY CENTRE | B43: 3000
A44: 45846 | B44: 3000
A45: 45855 | B45: 3000
A46: MACHAKOS | B46: 2000
A47: 45859 | B47: 2000
A48: HILL BRANCH | B48: 2000
A49: 45860 | B49: 2000
A50: MOMBASA | B50: 3000
A51: 45842 | B51: 3000
A52: KIAMBU | B52: 100
A53: 45842 | B53: 100
A54: ELDORET | B54: 2000
A55: 45842 | B55: 2000
A56: MTWAPA | B56: 2000
A57: 45847 | B57: 2000
A58: KITENGELA | B58: 3000
A59: 45849 | B59: 3000
A60: INDUSTRIAL AREA | B60: 2000
A61: 45862 | B61: 2000
A62: DONHOLM | B62: 3000
A63: 45860 | B63: 3000
A64: NAKURU | B64: 2000
A65: 45861 | B65: 2000
A66: Schedule of Contribution | B66: 1000
A67: KAKAMEGA | B67: 1000
A68: 45842 | B68: 1000
A69: Envelopes A5 | B69: 500
A70: FINANCE | B70: 200
A71: 45849 | B71: 200
A72: INVESTMENTS | B72: 200
A73: 45855 | B73: 200
A74: REGISTRATION & COMPLIANCE | B74: 100
A75: 45853 | B75: 100
A76: GM HR/ADM | B76: 500
A77: 45853 | B77: 500
A78: HUMAN CAPITAL/HR | B78: 200
A79: 45853 | B79: 200
A80: HR TALENT ACQUISITION | B80: 500
A81: 45853 | B81: 500
A82: ETHICS & INTEGRITY | B82: 50
A83: 45854 | B83: 50
A84: PROPERTY MANAGEMENT | B84: 10
A85: 45854 | B85: 10
A86: ADMINISTRATION | B86: 50
A87: 45860 | B87: 50
A88: MEMBER RECORDS | B88: 100
A89: 45861 | B89: 100
A90: Ben. App. Forms SF/001 | B90: 500
A91: WESTLANDS | B91: 400
A92: 45860 | B92: 400
A93: THIKA | B93: 500
A94: 45852 | B94: 500
A95: UKUNDA | B95: 400
A96: 45855 | B96: 400
A97: MACHAKOS | B97: 300
A98: 45859 | B98: 300
A99: HILL BRANCH | B99: 500
A100: 45860 | B100: 500
A101: KAKAMEGA | B101: 300
A102: 45842 | B102: 300
A103: KIAMBU | B103: 300
A104: 45859 | B104: 300
...

Sheet MIN CONSUMPTION
A3: Type | B3: (All)
A4: Department | B4: (All)
A6: Row Labels | B6: Min of In&Out Qty | C6: Min of In&Out Qty(%)
A7: Schedule of Contribution | B7: 1000 | C7: 10
A8: Membership Cards (Blank) | B8: 1000 | C8: 10
A9: Fingerprint Forms SF/003 | B9: 500 | C9: 5
A10: App. For Employer SF/001 | B10: 500 | C10: 5
A11: Registration Gen. Folders | B11: 200 | C11: 2
A12: Ben. App. Forms SF/001 | B12: 150 | C12: 1.5
A13: Payment of Benefit Forms/004 | B13: 100 | C13: 1
A14: Survivor Ben. Form | B14: 100 | C14: 1
A15: Laminating Pouches | B15: 100 | C15: 1
A16: Envelopes A4 | B16: 100 | C16: 1
A17: Grand Total | B17: 100 | C17: 1

Sheet INVENTORY ANALYSIS
A1: QUARTERLY FORTNIGHT REPORT FOR SF, COMPUTER & MAINTENANCE STORES
A2: Item Description | B2: Sum of In&Out Qty | C2: Sum of In&Out Qty(%)
A3: 45842 | B3: 21900 | C3: 0.20607886
A4: Issue | B4: 21900 | C4: 0.20607886
A5: Membership Cards (Blank) | B5: 9000 | C5: 0.084689941
A6: PCS | B6: 9000 | C6: 0.084689941
A7: MOMBASA | B7: 3000 | C7: 0.02822998
A8: KAKAMEGA | B8: 3000 | C8: 0.02822998
A9: ELDORET | B9: 3000 | C9: 0.02822998
A10: Laminating Pouches | B10: 5100 | C10: 0.047990966
A11: PCS | B11: 5100 | C11: 0.047990966
A12: MOMBASA | B12: 3000 | C12: 0.02822998
A13: KIAMBU | B13: 100 | C13: 0.00094099934
A14: ELDORET | B14: 2000 | C14: 0.018819987
A15: Fingerprint Forms SF/003 | B15: 2000 | C15: 0.018819987
... A48: MOMBASA | B48: 100 | C48: 0.00094099934
A49: 45846 | B49: 7000 | C49: 0.065869954
A50: Issue | B50: 7000 | C50: 0.065869954
A51: Laminating Pouches | B51: 3000 | C51: 0.02822998
A52: PCS | B52: 3000 | C52: 0.02822998
A53: CITY CENTRE | B53: 3000 | C53: 0.02822998
A54: Membership Cards (Blank) | B54: 3000 | C54: 0.02822998
A55: PCS | B55: 3000 | C55: 0.02822998
A56: CITY CENTRE | B56: 3000 | C56: 0.02822998
A57: Fingerprint Forms SF/003 | B57: 500 | C57: 0.0047049967
A58: PCS | B58: 500 | C58: 0.0047049967
A59: CITY CENTRE | B59: 500 | C59: 0.0047049967
A60: App. For Employer SF/001 | B60: 500 | C60: 0.0047049967
A61: PCS | B61: 500 | C61: 0.0047049967
A62: CITY CENTRE | B62: 500 | C62: 0.0047049967
A63: 45847 | B63: 8030 | C63: 0.075562247
A64: Issue | B64: 8030 | C64: 0.075562247
A65: Membership Cards (Blank) | B65: 5000 | C65: 0.047049967
A66: PCS | B66: 5000 | C66: 0.047049967
A67: KIAMBU | B67: 3000 | C67: 0.02822998
A68: MTWAPA | B68: 2000 | C68: 0.018819987
A69: Laminating Pouches | B69: 2000 | C69: 0.018819987
A70: PCS | B70: 2000 | C70: 0.018819987
A71: MTWAPA | B71: 2000 | C71: 0.018819987
A72: Fingerprint Forms SF/003 | B72: 500 | C72: 0.0047049967
A73: PCS | B73: 500 | C73: 0.0047049967
A74: MTWAPA | B74: 500 | C74: 0.0047049967
A75: Survivor Ben. Form | B75: 200 | C75: 0.0018819987
... A86: MTWAPA | B86: 80 | C86: 0.00075279947
A87: 45849 | B87: 10200 | C87: 0.095981933
A88: Issue | B88: 10200 | C88: 0.095981933
A89: Laminating Pouches | B89: 3000 | C89: 0.02822998
A90: PCS | B90: 3000 | C90: 0.02822998
A91: KITENGELA | B91: 3000 | C91: 0.02822998
A92: Membership Cards (Blank) | B92: 3000 | C92: 0.02822998
A93: PCS | B93: 3000 | C93: 0.02822998
A94: KITENGELA | B94: 3000 | C94: 0.02822998
A95: Payment of Benefit Forms/004 | B95: 1000 | C95: 0.0094099934
A96: PCS | B96: 1000 | C96: 0.0094099934
A97: HOMABAY | B97: 500 | C97: 0.0047049967
A98: KITENGELA | B98: 500 | C98: 0.0047049967
A99: Fingerprint Forms SF/003 | B99: 1000 | C99: 0.0094099934
... A124: HOMABAY | B124: 100 | C124: 0.00094099934
A125: 45852 | B125: 6300 | C125: 0.059282959
A126: Issue | B126: 6300 | C126: 0.059282959
A127: Laminating Pouches | B127: 4000 | C127: 0.037639974
A128: PCS | B128: 4000 | C128: 0.037639974
A129: THIKA | B129: 4000 | C129: 0.037639974
A130: Payment of Benefit Forms/004 | B130: 500 | C130: 0.0047049967
A131: PCS | B131: 500 | C131: 0.0047049967
A132: THIKA | B132: 500 | C132: 0.0047049967
A133: App. For Employer SF/001 | B133: 500 | C133: 0.0047049967
A134: PCS | B134: 500 | C134: 0.0047049967
A135: THIKA | B135: 500 | C135: 0.0047049967
A136: Ben. App. Forms SF/001 | B136: 500 | C136: 0.0047049967
A137: PCS | B137: 500 | C137: 0.0047049967
... A147: THIKA | B147: 200 | C147: 0.0018819987
A148: 45853 | B148: 3860 | C148: 0.036322575
A149: Issue | B149: 3860 | C149: 0.036322575
A150: Envelopes A5 | B150: 1300 | C150: 0.012232991
A151: PCS | B151: 1300 | C151: 0.012232991
A152: REGISTRATION & COMPLIANCE | B152: 100 | C152: 0.00094099934
A153: GM HR/ADM | B153: 500 | C153: 0.0047049967
A154: HUMAN CAPITAL/HR | B154: 200 | C154: 0.0018819987
A155: HR TALENT ACQUISITION | B155: 500 | C155: 0.0047049967
A156: Envelopes A4 | B156: 1300 | C156: 0.012232991
A157: PCS | B157: 1300 | C157: 0.012232991
A158: REGISTRATION & COMPLIANCE | B158: 200 | C158: 0.0018819987
A159: GM HR/ADM | B159: 500 | C159: 0.0047049967
A160: HR TALENT ACQUISITION | B160: 500 | C160: 0.0047049967
... A170: HUMAN CAPITAL/HR | B170: 60 | C170: 0.0005645996
A171: 45854 | B171: 210 | C171: 0.0019760986
A172: Issue | B172: 210 | C172: 0.0019760986
A173: Envelopes A4 | B173: 100 | C173: 0.00094099934
A174: PCS | B174: 100 | C174: 0.00094099934
A175: ETHICS & INTEGRITY | B175: 100 | C175: 0.00094099934
A176: Envelopes A5 | B176: 60 | C176: 0.0005645996
A177: PCS | B177: 60 | C177: 0.0005645996
A178: ETHICS & INTEGRITY | B178: 50 | C178: 0.00047049967
A179: PROPERTY MANAGEMENT | B179: 10 | C179: 9.4099934e-05
A180: Envelopes A3 (16*12) White | B180: 50 | C180: 0.00047049967
A181: PCS | B181: 50 | C181: 0.00047049967
A182: PROPERTY MANAGEMENT | B182: 50 | C182: 0.00047049967
A183: 45855 | B183: 10300 | C183: 0.096922932
A184: Issue | B184: 10300 | C184: 0.096922932
...

Sheet DASHBOARD
A2: INVENTORY ANALYSIS 2024
A3: MONTH | B3: TOTAL ISSUED | C3: TOTAL LOANED | D3: TOTAL RECEIVED
A4: January | B4: =SUMIFS(INOUTQTY,UnitsTable[Date],">="&DATE(2024,1,1),UnitsTable[Date],"<="&DATE(2024,1,31),UnitsTable[Type],"=Issue") -> 0 | C4: =SUMIFS(INOUTQTY,UnitsTable[Date],">="&DATE(2024,1,1),UnitsTable[Date],"<="&DATE(2024,4,31),UnitsTable[Type],"=Loaned") -> 0 | D4: =SUMIFS(INOUTQTY,UnitsTable[Date],">="&DATE(2024,1,1),UnitsTable[Date],"<="&DATE(2024,1,31),UnitsTable[Type],"=Receipt") -> 0
A5: February | B5: =SUMIFS(INOUTQTY,UnitsTable[Date],">="&DATE(2024,2,1),UnitsTable[Date],"<="&DATE(2024,2,29),UnitsTable[Type],"=Issue") -> 0 | C5: =SUMIFS(INOUTQTY,UnitsTable[Date],">="&DATE(2024,2,1),UnitsTable[Date],"<="&DATE(2024,2,29),UnitsTable[Type],"=Loaned") -> 0 | D5: =SUMIFS(INOUTQTY,UnitsTable[Date],">="&DATE(2024,2,1),UnitsTable[Date],"<="&DATE(2024,2,29),UnitsTable[Type],"=Receipt") -> 0
A6: March | B6: =SUMIFS(INOUTQTY,UnitsTable[Date],">="&DATE(2024,3,1),UnitsTable[Date],"<="&DATE(2024,3,31),UnitsTable[Type],"=Issue") -> 0 | C6: =SUMIFS(INOUTQTY,UnitsTable[Date],">="&DATE(2024,3,1),UnitsTable[Date],"<="&DATE(2024,3,31),UnitsTable[Type],"=Loaned") -> 0 | D6: =SUMIFS(INOUTQTY,UnitsTable[Date],">="&DATE(2024,3,1),UnitsTable[Date],"<="&DATE(2024,3,31),UnitsTable[Type],"=Receipt") -> 0
A7: April | B7: =SUMIFS(INOUTQTY,UnitsTable[Date],">="&DATE(2024,4,1),UnitsTable[Date],"<="&DATE(2024,4,30),UnitsTable[Type],"=Issue") -> 0 | C7: =SUMIFS(INOUTQTY,UnitsTable[Date],">="&DATE(2024,4,1),UnitsTable[Date],"<="&DATE(2024,4,30),UnitsTable[Type],"=Loaned") -> 0 | D7: =SUMIFS(INOUTQTY,UnitsTable[Date],">="&DATE(2024,4,1),UnitsTable[Date],"<="&DATE(2024,4,30),UnitsTable[Type],"=Receipt") -> 0
A8: May | B8: =SUMIFS(INOUTQTY,UnitsTable[Date],">="&DATE(2024,5,1),UnitsTable[Date],"<="&DATE(2024,5,31),UnitsTable[Type],"=Issue") -> 0 | C8: =SUMIFS(INOUTQTY,UnitsTable[Date],">="&DATE(2024,5,1),UnitsTable[Date],"<="&DATE(2024,5,31),UnitsTable[Type],"=Loaned") -> 0 | D8: =SUMIFS(INOUTQTY,UnitsTable[Date],">="&DATE(2024,5,1),UnitsTable[Date],"<="&DATE(2024,5,31),UnitsTable[Type],"=Receipt") -> 0
A9: June | B9: =SUMIFS(INOUTQTY,UnitsTable[Date],">="&DATE(2024,6,1),UnitsTable[Date],"<="&DATE(2024,6,30),UnitsTable[Type],"=Issue") -> 0 | C9: =SUMIFS(INOUTQTY,UnitsTable[Date],">="&DATE(2024,6,1),UnitsTable[Date],"<="&DATE(2024,6,30),UnitsTable[Type],"=Loaned") -> 0 | D9: =SUMIFS(INOUTQTY,UnitsTable[Date],">="&DATE(2024,6,1),UnitsTable[Date],"<="&DATE(2024,6,30),UnitsTable[Type],"=Receipt") -> 0
A10: July | B10: =SUMIFS(INOUTQTY,UnitsTable[Date],">="&DATE(2024,7,1),UnitsTable[Date],"<="&DATE(2024,7,31),UnitsTable[Type],"=Issue") -> 0 | C10: =SUMIFS(INOUTQTY,UnitsTable[Date],">="&DATE(2024,7,1),UnitsTable[Date],"<="&DATE(2024,7,31),UnitsTable[Type],"=Loaned") -> 0 | D10: =SUMIFS(INOUTQTY,UnitsTable[Date],">="&DATE(2024,7,1),UnitsTable[Date],"<="&DATE(2024,7,31),UnitsTable[Type],"=Receipt") -> 0
A11: August | B11: =SUMIFS(INOUTQTY,UnitsTable[Date],">="&DATE(2024,8,1),UnitsTable[Date],"<="&DATE(2024,8,31),UnitsTable[Type],"=Issue") -> 0 | C11: =SUMIFS(INOUTQTY,UnitsTable[Date],">="&DATE(2024,8,1),UnitsTable[Date],"<="&DATE(2024,8,31),UnitsTable[Type],"=Loaned") -> 0 | D11: =SUMIFS(INOUTQTY,UnitsTable[Date],">="&DATE(2024,8,1),UnitsTable[Date],"<="&DATE(2024,8,30),UnitsTable[Type],"=Receipt") -> 0
A12: September | B12: =SUMIFS(INOUTQTY,UnitsTable[Date],">="&DATE(2024,9,1),UnitsTable[Date],"<="&DATE(2024,9,30),UnitsTable[Type],"=Issue") -> 0 | C12: =SUMIFS(INOUTQTY,UnitsTable[Date],">="&DATE(2024,9,1),UnitsTable[Date],"<="&DATE(2024,9,30),UnitsTable[Type],"=Loaned") -> 0 | D12: =SUMIFS(INOUTQTY,UnitsTable[Date],">="&DATE(2024,9,1),UnitsTable[Date],"<="&DATE(2024,6,30),UnitsTable[Type],"=Receipt") -> 0
A13: October | B13: =SUMIFS(INOUTQTY,UnitsTable[Date],">="&DATE(2024,10,1),UnitsTable[Date],"<="&DATE(2024,10,31),UnitsTable[Type],"=Issue") -> 0 | C13: =SUMIFS(INOUTQTY,UnitsTable[Date],">="&DATE(2024,10,1),UnitsTable[Date],"<="&DATE(2024,10,31),UnitsTable[Type],"=Loaned") -> 0 | D13: =SUMIFS(INOUTQTY,UnitsTable[Date],">="&DATE(2024,10,1),UnitsTable[Date],"<="&DATE(2024,10,31),UnitsTable[Type],"=Receipt") -> 0
A14: November | B14: =SUMIFS(INOUTQTY,UnitsTable[Date],">="&DATE(2024,11,1),UnitsTable[Date],"<="&DATE(2024,11,30),UnitsTable[Type],"=Issue") -> 0 | C14: =SUMIFS(INOUTQTY,UnitsTable[Date],">="&DATE(2024,11,1),UnitsTable[Date],"<="&DATE(2024,11,30),UnitsTable[Type],"=Loaned") -> 0 | D14: =SUMIFS(INOUTQTY,UnitsTable[Date],">="&DATE(2024,11,1),UnitsTable[Date],"<="&DATE(2024,11,30),UnitsTable[Type],"=Receipt") -> 0
A15: December | B15: =SUMIFS(INOUTQTY,UnitsTable[Date],">="&DATE(2024,12,1),UnitsTable[Date],"<="&DATE(2024,12,31),UnitsTable[Type],"=Issue") -> 0 | C15: =SUMIFS(INOUTQTY,UnitsTable[Date],">="&DATE(2024,12,1),UnitsTable[Date],"<="&DATE(2024,12,31),UnitsTable[Type],"=Loaned") -> 0 | D15: =SUMIFS(INOUTQTY,UnitsTable[Date],">="&DATE(2024,12,1),UnitsTable[Date],"<="&DATE(2024,12,31),UnitsTable[Type],"=Receipt") -> 0
